{"status": "ok", "message": "done", "result": {"bio": {"tab_canhan": {"ca_nhan": {"hovaten": "CÙ THỊ XUÂN", "gioitinh": "2", "ngaysinh": "10/09/1981", "id_noisinh": "38", "noisinh": "Thanh Hóa", "id_tinh": "38", "tinh": "Thanh Hóa", "huyen": "392", "xa": "15307", "id_tinh1": "79", "tinh1": "TP. Hồ Chí Minh", "huyen1": "761", "xa1": "26767", "duong": "141/36/34", "cccd": "038181000612", "ngay_cccd": "21/12/2021", "id_dantoc": "01", "dantoc": "Kinh (Việt)", "tongiao": "99", "avata": "", "avata_data_type": "", "filename": "", "type": "vc", "unitCode": "XHNV"}, "cong_tac": {"ngay": "01/08/2008", "dt": "0982402758", "email": "cuthixuan@hcmussh.edu.vn", "ngay_dang": "17/01/2011", "ngay_ct": "17/01/2012", "id_trinhdo": "22", "chuyenmon": "04", "id_danhhieu": "", "danhhieu": "", "hocham": "", "macb": "QSX8100893"}, "chuc_vu": {"id_chucvu": "", "chucvu": "", "congviec": "Chuyên viên", "id_dang": "", "cv_dang": "", "id_ngach": "01.003", "ngach": "Chuyên viên", "maso": "", "ngay_bonhiem": "01/01/2012", "bacluong": "05", "heso": "3.66", "ngay_huong": "01/10/2021", "pt_huong": "không", "phu_cap": "không", "ngay_phucap": ""}, "viec_lam": {"vitri": "", "maso": "", "bacluong": "", "luong": "", "ngay_huong": "", "pt_huong": "", "phu_cap": "", "ngay_phucap": ""}}, "tab_hocvan": {"hv_chuyenmon": [{"id": "", "begin": "06/2004", "end": "08/2007", "id_place": "", "place": "Trường ĐHKHXH&NV TPHCM", "id_chuyennganh": "", "chuyennganh": "LT-QTVP", "id_hinhthuc": "TC", "id_vanbang": "04", "vanbang": ""}], "hv_llct": [], "hv_ngoaingu": [{"id": "", "begin": "08/2012", "end": "08/2012", "id_place": "", "place": "Trường ĐHKHXH&NV TP.HCM", "id_ngonngu": "01", "chunh_chi": "B", "diem": "Chưa xác định"}], "hv_tinhoc": [{"id": "", "begin": "9/2012", "end": "9/2012", "id_place": "", "place": "Trường ĐHKHXH&NV TP.HCM", "chunh_chi": "A"}]}, "tab_congtac": {"ct_donvi": [{"id": "", "begin": "08/2008", "end": "04/2024", "place": "Trường ĐHKHXh&NV", "chucvu": "Chuyên viên"}]}, "tab_tieusu": {"ts_cdc": [], "ts_nuocngoai": []}, "tab_khenthuong": {"kt_khen": [{"id": "1", "year": "2009", "id_chuyenmon": "01", "loai_td": "Danh hiệu Lao động tiên tiến", "id_hinhthuc": "07"}, {"id": "2", "year": "2010", "id_chuyenmon": "01", "loai_td": "Danh hiệu Lao động tiên tiến", "id_hinhthuc": "07"}, {"id": "3", "year": "2012", "id_chuyenmon": "01", "loai_td": "Danh hiệu Lao động tiên tiến", "id_hinhthuc": "07"}, {"id": "4", "year": "2012", "id_chuyenmon": "01", "loai_td": "Giấy khen của Hiệu trưởng", "id_hinhthuc": "06"}, {"id": "5", "year": "2013", "id_chuyenmon": "01", "loai_td": "Danh hiệu Lao động tiên tiến", "id_hinhthuc": "07"}, {"id": "6", "year": "2014", "id_chuyenmon": "01", "loai_td": "Danh hiệu Lao động tiên tiến", "id_hinhthuc": "07"}, {"id": "7", "year": "2014", "id_chuyenmon": "01", "loai_td": "Giấy khen của Hiệu trưởng", "id_hinhthuc": "06"}, {"id": "8", "year": "2015", "id_chuyenmon": "01", "loai_td": "Danh hiệu Lao động tiên tiến", "id_hinhthuc": "07"}, {"id": "9", "year": "2015", "id_chuyenmon": "01", "loai_td": "Giấy khen của Hiệu trưởng", "id_hinhthuc": "06"}, {"id": "10", "year": "2016", "id_chuyenmon": "01", "loai_td": "Danh hiệu Lao động tiên tiến", "id_hinhthuc": "07"}, {"id": "11", "year": "2016", "id_chuyenmon": "01", "loai_td": "Giấy khen của Hiệu trưởng", "id_hinhthuc": "06"}, {"id": "12", "year": "2017", "id_chuyenmon": "01", "loai_td": "Danh hiệu Lao động tiên tiến", "id_hinhthuc": "07"}, {"id": "13", "year": "2017", "id_chuyenmon": "01", "loai_td": "Giấy khen của Hiệu trưởng", "id_hinhthuc": "06"}, {"id": "14", "year": "2018", "id_chuyenmon": "01", "loai_td": "Danh hiệu Lao động tiên tiến", "id_hinhthuc": "07"}, {"id": "15", "year": "2018", "id_chuyenmon": "01", "loai_td": "Giấy khen của Hiệu trưởng", "id_hinhthuc": "06"}, {"id": "16", "year": "2019", "id_chuyenmon": "01", "loai_td": "Danh hiệu Lao động tiên tiến", "id_hinhthuc": "07"}, {"id": "17", "year": "2019", "id_chuyenmon": "01", "loai_td": "Giấy khen của Hiệu trưởng", "id_hinhthuc": "06"}, {"id": "18", "year": "2020", "id_chuyenmon": "01", "loai_td": "Danh hiệu Lao động tiên tiến", "id_hinhthuc": "07"}, {"id": "19", "year": "2020", "id_chuyenmon": "01", "loai_td": "Giấy khen của Hiệu trưởng", "id_hinhthuc": "06"}, {"id": "20", "year": "2021", "id_chuyenmon": "01", "loai_td": "Danh hiệu Lao động tiên tiến", "id_hinhthuc": "07"}, {"id": "21", "year": "2021", "id_chuyenmon": "01", "loai_td": "Giấy khen của Hiệu trưởng", "id_hinhthuc": "06"}, {"id": "22", "year": "2022", "id_chuyenmon": "01", "loai_td": "Danh hiệu Lao động tiên tiến", "id_hinhthuc": "07"}, {"id": "23", "year": "2022", "id_chuyenmon": "01", "loai_td": "Giấy khen của Hiệu trưởng", "id_hinhthuc": "06"}, {"id": "24", "year": "2023", "id_chuyenmon": "01", "loai_td": "Danh hiệu Lao động tiên tiến", "id_hinhthuc": "07"}, {"id": "25", "year": "2023", "id_chuyenmon": "01", "loai_td": "Giấy khen của Hiệu trưởng", "id_hinhthuc": "06"}], "kt_kyluat": []}, "tab_giacanh": {"gc_banthan": [{"id": "", "id_qh": "03", "name": "Cù Văn Cảnh", "year": "1954", "detail": "Hưu trí xã Yến Sơn- huyện Hà Trung- tỉnh Thanh Hóa"}, {"id": 2, "id_qh": "04", "name": "Lê Thị Mai", "year": "1954", "detail": "Hưu trí tại xã Yến Sơn huyện Hà Trung- tỉnh Thanh Hóa"}, {"id": 5, "id_qh": "10", "name": "Cù Văn Sơn", "year": "1986", "detail": "Công nhân tại xã Yến Sơn- huyện Hà Trung- tỉnh Thanh Hóa"}, {"id": 6, "id_qh": "10", "name": "Cù Văn Ngọc", "year": "1987", "detail": "Công nhân tại xã Yến Sơn- huyện Hà Trung- tỉnh Thanh Hóa"}, {"id": 7, "id_qh": "06", "name": "Nguyễn Giang Nam", "year": "1980", "detail": "Hà Nội, Kiến trúc sư , Trung tâm quản lý nhà thuộc Sở xây dựng TP.HCM"}, {"id": 8, "id_qh": "07", "name": "Nguyễn Nam Khánh", "year": "2008", "detail": "Học Sinh"}, {"id": 9, "id_qh": "07", "name": "Nguyễn Khánh My", "year": "2012", "detail": "Học sinh"}], "gc_giadinh": [{"id": 3, "id_qh": "03", "name": "Nguyễn Hữu Bút", "year": "1948", "detail": "Đã mất tại xã Mạch Lũng- Đại Mạch, Đông Anh , Hà Nội"}, {"id": 10, "id_qh": "04", "name": "Lưu Thị Phương", "year": "1957", "detail": "Hưu trí tại Kiên Giang"}, {"id": 11, "id_qh": "10", "name": "Nguyễn Việt Bắc", "year": "1983", "detail": "Giáo viên tại Kiên Giang"}, {"id": 12, "id_qh": "10", "name": "Nguyễn Thị Bích", "year": "1990", "detail": "Làm việc tại Kiên Giang"}], "gc_luong": [{"id": "1", "begin": "08/2008", "end": "09/2009", "maso": "01.003", "bacluong": "01", "heso": "2.34 (85%)", "tienluong": "Chưa xác định"}, {"id": "2", "begin": "10/2009", "end": "09/2012", "maso": "01.003", "bacluong": "01", "heso": "2.34", "tienluong": "Chưa xác định"}, {"id": "3", "begin": "10/2012", "end": "09/2015", "maso": "01.003", "bacluong": "02", "heso": "2.67", "tienluong": "Chưa xác định"}, {"id": "4", "begin": "10/2015", "end": "09/2018", "maso": "01.003", "bacluong": "03", "heso": "3", "tienluong": "Chưa xác định"}, {"id": "5", "begin": "10/2018", "end": "09/2021", "maso": "01.003", "bacluong": "04", "heso": "3.33", "tienluong": "Chưa xác định"}, {"id": "6", "begin": "10/2021", "end": "05/2022", "maso": "01.003", "bacluong": "05", "heso": "3.66", "tienluong": "Chưa xác định"}], "gc_phucap": [], "gc_taisan": [{"id": 3, "loai": "00", "dientich": "", "giay": ""}]}}}}