{"status": "ok", "message": "done", "result": {"bio": {"tab_canhan": {"ca_nhan": {"hovaten": "NGUYỄN THỊ NGỌC BÍCH", "gioitinh": "2", "ngaysinh": "02/09/1969", "id_noisinh": "38", "noisinh": "Thanh Hóa", "id_tinh": "80", "tinh": "Long An", "huyen": "802", "xa": "27931", "id_tinh1": "79", "tinh1": "TP. Hồ Chí Minh", "huyen1": "760", "xa1": "26740", "duong": "14/9F Lý Tự Trọng", "cccd": "038169014927", "ngay_cccd": "10/7/2021", "id_dantoc": "01", "dantoc": "Kinh (Việt)", "tongiao": "99", "avata": "", "avata_data_type": "", "filename": "", "type": "hdld", "unitCode": "XHNV"}, "cong_tac": {"ngay": "04/04/1996", "dt": "0938091566", "email": "nguyenthingocbich@hcmussh.edu.vn", "ngay_dang": "", "ngay_ct": "", "id_trinhdo": "22", "chuyenmon": "08", "id_danhhieu": "", "danhhieu": "", "hocham": "", "macb": "QSX6900047"}, "chuc_vu": {"id_chucvu": "", "chucvu": "", "congviec": "Nhân viên vệ sinh kho sách", "id_dang": "", "cv_dang": "", "id_ngach": "", "ngach": "", "maso": "", "ngay_bonhiem": "", "bacluong": "", "heso": "", "ngay_huong": "", "pt_huong": "", "phu_cap": "", "ngay_phucap": ""}, "viec_lam": {"vitri": "", "maso": "", "bacluong": "", "luong": "", "ngay_huong": "", "pt_huong": "", "phu_cap": "", "ngay_phucap": ""}}, "tab_hocvan": {"hv_chuyenmon": [{"id": 2, "begin": "04/1996", "end": "04/2024", "id_place": "", "place": "Không có", "id_chuyennganh": "", "chuyennganh": "Không có", "id_hinhthuc": "CXD", "id_vanbang": "09", "vanbang": ""}], "hv_llct": [], "hv_ngoaingu": [], "hv_tinhoc": []}, "tab_congtac": {"ct_donvi": [{"id": 2, "begin": "04/1996", "end": "04/2024", "place": "Trường Đại học Khoa học Xã hội và Nhân văn", "chucvu": "Nhân viên"}]}, "tab_tieusu": {"ts_cdc": [], "ts_nuocngoai": []}, "tab_khenthuong": {"kt_khen": [{"id": "1", "year": "2008", "id_chuyenmon": "01", "loai_td": "Danh hiệu Lao động tiên tiến", "id_hinhthuc": "07"}, {"id": "2", "year": "2012", "id_chuyenmon": "01", "loai_td": "Danh hiệu Lao động tiên tiến", "id_hinhthuc": "07"}, {"id": "3", "year": "2013", "id_chuyenmon": "01", "loai_td": "Danh hiệu Lao động tiên tiến", "id_hinhthuc": "07"}, {"id": "4", "year": "2014", "id_chuyenmon": "01", "loai_td": "Danh hiệu Lao động tiên tiến", "id_hinhthuc": "07"}, {"id": "5", "year": "2015", "id_chuyenmon": "01", "loai_td": "Danh hiệu Lao động tiên tiến", "id_hinhthuc": "07"}, {"id": "6", "year": "2016", "id_chuyenmon": "01", "loai_td": "Danh hiệu Lao động tiên tiến", "id_hinhthuc": "07"}, {"id": "7", "year": "2016", "id_chuyenmon": "01", "loai_td": "Giấy khen của Hiệu trưởng", "id_hinhthuc": "06"}, {"id": "8", "year": "2017", "id_chuyenmon": "01", "loai_td": "Danh hiệu Lao động tiên tiến", "id_hinhthuc": "07"}, {"id": "9", "year": "2017", "id_chuyenmon": "01", "loai_td": "Giấy khen của Hiệu trưởng", "id_hinhthuc": "06"}, {"id": "10", "year": "2018", "id_chuyenmon": "01", "loai_td": "Danh hiệu Lao động tiên tiến", "id_hinhthuc": "07"}, {"id": "11", "year": "2018", "id_chuyenmon": "01", "loai_td": "Giấy khen của Hiệu trưởng", "id_hinhthuc": "06"}, {"id": "12", "year": "2018", "id_chuyenmon": "01", "loai_td": "Kỷ niệm chương Vì sự nghiệp giáo dục", "id_hinhthuc": "04"}, {"id": "13", "year": "2019", "id_chuyenmon": "01", "loai_td": "Danh hiệu Lao động tiên tiến", "id_hinhthuc": "07"}, {"id": "14", "year": "2019", "id_chuyenmon": "01", "loai_td": "Giấy khen của Hiệu trưởng", "id_hinhthuc": "06"}, {"id": "15", "year": "2020", "id_chuyenmon": "01", "loai_td": "Danh hiệu Lao động tiên tiến", "id_hinhthuc": "07"}, {"id": "16", "year": "2020", "id_chuyenmon": "01", "loai_td": "Giấy khen của Hiệu trưởng", "id_hinhthuc": "06"}, {"id": "17", "year": "2021", "id_chuyenmon": "01", "loai_td": "Danh hiệu Lao động tiên tiến", "id_hinhthuc": "07"}, {"id": "18", "year": "2021", "id_chuyenmon": "01", "loai_td": "Giấy khen của Hiệu trưởng", "id_hinhthuc": "06"}, {"id": "19", "year": "2022", "id_chuyenmon": "01", "loai_td": "Danh hiệu Lao động tiên tiến", "id_hinhthuc": "07"}, {"id": "20", "year": "2022", "id_chuyenmon": "01", "loai_td": "Giấy khen của Hiệu trưởng", "id_hinhthuc": "06"}, {"id": "21", "year": "2023", "id_chuyenmon": "01", "loai_td": "Danh hiệu Lao động tiên tiến", "id_hinhthuc": "07"}, {"id": "22", "year": "2023", "id_chuyenmon": "01", "loai_td": "Giấy khen của Hiệu trưởng", "id_hinhthuc": "06"}], "kt_kyluat": []}, "tab_giacanh": {"gc_banthan": [{"id": "", "id_qh": "06", "name": "Bùi Văn Minh", "year": "1958", "detail": "Tp Hồ Chí Minh, Mất sức lao động"}, {"id": 2, "id_qh": "07", "name": "Bùi Nguyên Minh Hiếu", "year": "1989", "detail": "Tp Hồ Chí Minh, nhân viên"}, {"id": 5, "id_qh": "07", "name": "Bùi Nguyên Minh Thuận", "year": "1998", "detail": "Tp Hồ Chí Minh,kỷ sư cơ khí"}], "gc_giadinh": [{"id": 3, "id_qh": "03", "name": "Bùi Văn Hiển", "year": "1928", "detail": "Mất"}, {"id": 6, "id_qh": "04", "name": "Nguyễn Thị Hiếm", "year": "1930", "detail": "Mất"}, {"id": 7, "id_qh": "09", "name": "Bùi Thị Kim Thịnh", "year": "1954", "detail": "Hưu trí"}, {"id": 8, "id_qh": "10", "name": "Bùi Minh Mẫn", "year": "1968", "detail": "Nhân viên bảo vệ"}], "gc_luong": [], "gc_phucap": [{"id": "1", "begin": "04/1996", "end": "04/2024", "id_loai": "04", "phantram": "100%", "heso": "0.2", "hinhthuc": "Hàng tháng", "tienluong": "Chưa xác định"}], "gc_taisan": [{"id": "", "loai": "5", "dientich": "48", "giay": "Chưa xác định"}]}}}}