{"status": "ok", "message": "done", "result": {"bio": {"tab_canhan": {"ca_nhan": {"hovaten": "VÕ NGỌC TUẤN KIỆT", "gioitinh": "1", "ngaysinh": "14/04/1971", "id_noisinh": "79", "noisinh": "TP. Hồ Chí Minh", "id_tinh": "79", "tinh": "TP. Hồ Chí Minh", "huyen": "770", "xa": "27151", "id_tinh1": "79", "tinh1": "TP. Hồ Chí Minh", "huyen1": "775", "xa1": "27361", "duong": "8/28A Minh Phụng", "cccd": "079071009400", "ngay_cccd": "26/12/2021", "id_dantoc": "01", "dantoc": "Kinh (Việt)", "tongiao": "99", "avata": "", "avata_data_type": "", "filename": "", "type": "vc", "unitCode": "XHNV"}, "cong_tac": {"ngay": "15/04/2006", "dt": "0918996186", "email": "vongoctuankiet@hcmussh.edu.vn", "ngay_dang": "", "ngay_ct": "", "id_trinhdo": "22", "chuyenmon": "03", "id_danhhieu": "", "danhhieu": "", "hocham": "", "macb": "QSX7110337"}, "chuc_vu": {"id_chucvu": "", "chucvu": "", "congviec": "Giảng viên", "id_dang": "", "cv_dang": "", "id_ngach": "V.07.01.03", "ngach": "Giảng viên", "maso": "", "ngay_bonhiem": "01/12/2008", "bacluong": "07", "heso": "4.32", "ngay_huong": "01/04/2023", "pt_huong": "không", "phu_cap": "không", "ngay_phucap": ""}, "viec_lam": {"vitri": "", "maso": "", "bacluong": "", "luong": "", "ngay_huong": "", "pt_huong": "", "phu_cap": "", "ngay_phucap": ""}}, "tab_hocvan": {"hv_chuyenmon": [{"id": "", "begin": "9/1998", "end": "7/2002", "id_place": "", "place": "ĐH.QGTPHCM - Trường ĐH.Khoa học Xã hội & Nhân văn", "id_chuyennganh": "9220204", "chuyennganh": "Ngôn ngữ Trung Quốc", "id_hinhthuc": "00", "id_vanbang": "04", "vanbang": ""}, {"id": 2, "begin": "9/2003", "end": "7/2005", "id_place": "", "place": "Đại học Nam Hoa (Đài Loan)", "id_chuyennganh": "", "chuyennganh": "Nghiên cứu Châu Á - Thái Bình Dương", "id_hinhthuc": "00", "id_vanbang": "03", "vanbang": ""}], "hv_llct": [], "hv_ngoaingu": [{"id": 5, "begin": "9/2007", "end": "9/2007", "id_place": "", "place": "ĐH.QGTP.HCM Trường ĐH. Khoa học Xã hội & Nhân văn", "id_ngonngu": "01", "chunh_chi": "B", "diem": "Không xác định"}], "hv_tinhoc": [{"id": "", "begin": "6/2007", "end": "6/2007", "id_place": "", "place": "ĐH.QGTP.HCM Trường ĐH. Khoa học Xã hội & Nhân văn", "chunh_chi": "A"}]}, "tab_congtac": {"ct_donvi": [{"id": "", "begin": "2/1993", "end": "3/1997", "place": "Công ty sản xuất hàng tiêu dùng Bình Tiên", "chucvu": "Công nhân"}, {"id": 2, "begin": "4/1997", "end": "5/2001", "place": "Nhà sách Nguyễn Thái Sơn", "chucvu": "Nhân viên"}, {"id": 3, "begin": "9/2005", "end": "4/2024", "place": "Trường ĐH.KHoa học Xã hội & Nhân văn", "chucvu": "Giảng viên"}]}, "tab_tieusu": {"ts_cdc": [], "ts_nuocngoai": []}, "tab_khenthuong": {"kt_khen": [{"id": "1", "year": "2006", "id_chuyenmon": "02", "loai_td": "Giấy khen của Hiệu trưởng", "id_hinhthuc": "06"}, {"id": "2", "year": "2007", "id_chuyenmon": "02", "loai_td": "Giấy khen của Hiệu trưởng", "id_hinhthuc": "06"}, {"id": "3", "year": "2008", "id_chuyenmon": "02", "loai_td": "Giấy khen của Hiệu trưởng", "id_hinhthuc": "06"}, {"id": "4", "year": "2009", "id_chuyenmon": "02", "loai_td": "Giấy khen của Hiệu trưởng", "id_hinhthuc": "06"}, {"id": "5", "year": "2010", "id_chuyenmon": "02", "loai_td": "Giấy khen của Hiệu trưởng", "id_hinhthuc": "06"}, {"id": 4, "year": "2011", "id_chuyenmon": "02", "loai_td": "Giấy khen của Hiệu trưởng", "id_hinhthuc": "06"}, {"id": 5, "year": "2011", "id_chuyenmon": "02", "loai_td": "Giấy khen của Hiệu trưởng", "id_hinhthuc": "06"}, {"id": 6, "year": "2012", "id_chuyenmon": "02", "loai_td": "Giấy khen của Hiệu trưởng", "id_hinhthuc": "06"}, {"id": 7, "year": "2013", "id_chuyenmon": "02", "loai_td": "Giấy khen của Hiệu trưởng", "id_hinhthuc": "06"}, {"id": 8, "year": "2014", "id_chuyenmon": "02", "loai_td": "Giấy khen của Hiệu trưởng", "id_hinhthuc": "06"}, {"id": 9, "year": "2015", "id_chuyenmon": "02", "loai_td": "Giấy khen của Hiệu trưởng", "id_hinhthuc": "06"}, {"id": 10, "year": "2016", "id_chuyenmon": "02", "loai_td": "Giấy khen của Hiệu trưởng", "id_hinhthuc": "06"}, {"id": 11, "year": "2017", "id_chuyenmon": "02", "loai_td": "Giấy khen của Hiệu trưởng", "id_hinhthuc": "06"}, {"id": 12, "year": "2018", "id_chuyenmon": "02", "loai_td": "Giấy khen cue3 Hiệu trưởng", "id_hinhthuc": "06"}, {"id": 13, "year": "2019", "id_chuyenmon": "02", "loai_td": "Giấy khen của Hiệu trưởng", "id_hinhthuc": "06"}, {"id": 14, "year": "2020", "id_chuyenmon": "02", "loai_td": "Giấy khen của Hiệu trưởng", "id_hinhthuc": "06"}, {"id": 15, "year": "2021", "id_chuyenmon": "02", "loai_td": "Giấy khen của Hiệu trưởng", "id_hinhthuc": "06"}, {"id": 16, "year": "2022", "id_chuyenmon": "02", "loai_td": "Giấy khen của Hiệu trưởng", "id_hinhthuc": "06"}, {"id": 17, "year": "2023", "id_chuyenmon": "02", "loai_td": "Giấy khen của Hiệu trưởng", "id_hinhthuc": "06"}], "kt_kyluat": []}, "tab_giacanh": {"gc_banthan": [{"id": "", "id_qh": "03", "name": "Võ Ngọc Kiệm", "year": "1939", "detail": "Đã mất"}, {"id": 2, "id_qh": "04", "name": "Nguyễn Thị Cúc", "year": "1946", "detail": "Đã mất"}, {"id": 5, "id_qh": "10", "name": "Võ Ngọc Trân Châu", "year": "1973", "detail": "Nội trợ"}, {"id": 6, "id_qh": "10", "name": "Võ Ngọc Bửu Kiếm", "year": "1974", "detail": "Công nhân viên"}, {"id": 7, "id_qh": "10", "name": "Võ Ngọc Kim Chi", "year": "1975", "detail": "Buôn bán nhỏ"}, {"id": 8, "id_qh": "10", "name": "Võ Ngọc Kim Cương", "year": "1978", "detail": "Buôn bán nhỏ"}, {"id": 9, "id_qh": "05", "name": "Lê Thị Hạnh Dung", "year": "1970", "detail": "Nội trợ"}, {"id": 10, "id_qh": "07", "name": "Võ Đắc Vi Nhân", "year": "1998", "detail": "Sinh viên"}, {"id": 11, "id_qh": "07", "name": "Võ Đắc Minh Tâm", "year": "2004", "detail": "Sinh viên"}], "gc_giadinh": [{"id": 3, "id_qh": "03", "name": "Nguyễn Văn Tứ", "year": "1942", "detail": "Đã mất"}, {"id": 12, "id_qh": "04", "name": "Lê Thị Hai", "year": "1949", "detail": "Già yếu"}, {"id": 13, "id_qh": "10", "name": "Lê Thị Kim Chi", "year": "1971", "detail": "Công nhân viên"}, {"id": 14, "id_qh": "10", "name": "Lê Thị Bạch Trúc", "year": "1973", "detail": "Kinh doanh nhỏ"}, {"id": 15, "id_qh": "10", "name": "Nguyễn Văn Phước", "year": "1974", "detail": "Công nhân viên"}, {"id": 16, "id_qh": "10", "name": "Nguyễn Thị Mỹ Duyên", "year": "1976", "detail": "Công nhân viên"}, {"id": 17, "id_qh": "10", "name": "Nguyễn Văn Đức", "year": "1978", "detail": "Công nhân viên"}, {"id": 18, "id_qh": "10", "name": "Nguyễn Văn Trí", "year": "1981", "detail": "Công nhân viên"}], "gc_luong": [{"id": "1", "begin": "04/2007", "end": "11/2008", "maso": "15.111", "bacluong": "01", "heso": "2.34", "tienluong": "Chưa xác định"}, {"id": "2", "begin": "12/2008", "end": "03/2011", "maso": "15.111", "bacluong": "02", "heso": "2.67", "tienluong": "Chưa xác định"}, {"id": "3", "begin": "04/2011", "end": "03/2014", "maso": "15.111", "bacluong": "03", "heso": "3", "tienluong": "Chưa xác định"}, {"id": "4", "begin": "04/2014", "end": "03/2017", "maso": "15.111", "bacluong": "04", "heso": "3.33", "tienluong": "Chưa xác định"}, {"id": "5", "begin": "04/2017", "end": "03/2020", "maso": "V.07.01.03", "bacluong": "05", "heso": "3.66", "tienluong": "Chưa xác định"}, {"id": "6", "begin": "04/2020", "end": "03/2023", "maso": "V.07.01.03", "bacluong": "06", "heso": "3.99", "tienluong": "Chưa xác định"}, {"id": "7", "begin": "04/2023", "end": "04/2024", "maso": "V.07.01.03", "bacluong": "07", "heso": "4.32", "tienluong": "Chưa xác định"}], "gc_phucap": [{"id": "1", "begin": "1/2024", "end": "4/2024", "id_loai": "13", "phantram": "0.15", "heso": "6.20", "hinhthuc": "Hàng tháng", "tienluong": "Chưa xác định"}, {"id": 19, "begin": "1/2024", "end": "4/2024", "id_loai": "11", "phantram": "0.25", "heso": "6.20", "hinhthuc": "Hàng tháng", "tienluong": "Chưa xác định"}], "gc_taisan": [{"id": "", "loai": "4", "dientich": "30,8m2", "giay": "Hồ sơ số: 27046.28490.TK"}]}}}}