{"status": "ok", "message": "done", "result": {"bio": {"tab_canhan": {"ca_nhan": {"hovaten": "LÊ THANH HÒA", "gioitinh": "1", "ngaysinh": "16/07/1970", "id_noisinh": "79", "noisinh": "TP. Hồ Chí Minh", "id_tinh": "87", "tinh": "Đồng Tháp", "huyen": "867", "xa": "29919", "id_tinh1": "79", "tinh1": "TP. Hồ Chí Minh", "huyen1": "764", "xa1": "26896", "duong": "567/2A Lê QUang Địnnh", "cccd": "079070004383", "ngay_cccd": "26/09/2022", "id_dantoc": "01", "dantoc": "Kinh (Việt)", "tongiao": "01", "avata": "", "avata_data_type": "", "filename": "", "type": "vcql", "unitCode": "XHNV"}, "cong_tac": {"ngay": "01/09/1996", "dt": "0914150015", "email": "hoalethanh@hcmussh.edu.vn", "ngay_dang": "", "ngay_ct": "", "id_trinhdo": "22", "chuyenmon": "02", "id_danhhieu": "", "danhhieu": "", "hocham": "", "macb": "QSX7010253"}, "chuc_vu": {"id_chucvu": "118", "chucvu": "Trưởng khoa và tương đương trực thuộc trường", "congviec": "Trưởng khoa", "id_dang": "", "cv_dang": "", "id_ngach": "V.07.01.02", "ngach": "Phó giáo sư - giảng viên chính", "maso": "", "ngay_bonhiem": "", "bacluong": "06", "heso": "6.10", "ngay_huong": "01/02/2023", "pt_huong": "không", "phu_cap": "không", "ngay_phucap": ""}, "viec_lam": {"vitri": "", "maso": "", "bacluong": "", "luong": "", "ngay_huong": "", "pt_huong": "", "phu_cap": "", "ngay_phucap": ""}}, "tab_hocvan": {"hv_chuyenmon": [{"id": "", "begin": "06/1992", "end": "06/1995", "id_place": "", "place": "Đại học tổng hợp TPHCM", "id_chuyennganh": "", "chuyennganh": "Địa lý", "id_hinhthuc": "00", "id_vanbang": "04", "vanbang": ""}, {"id": 2, "begin": "09/1999", "end": "09/2001", "id_place": "", "place": "Đại học Khoa học Xã hội và Nhân văn-ĐHQGHCM", "id_chuyennganh": "", "chuyennganh": "Bảo vệ sử dụng hợp lý và tái tạo tài nguyên thiên nhiên", "id_hinhthuc": "00", "id_vanbang": "03", "vanbang": ""}, {"id": 4, "begin": "11/2009", "end": "01/2014", "id_place": "", "place": "Trường Đại Học Khoa Học Công Nghệ BTU Cottbus – Brandenburge – Germany", "id_chuyennganh": "", "chuyennganh": "Qui hoạch và quản lý tài nguyên môi truờng", "id_hinhthuc": "TT", "id_vanbang": "02", "vanbang": ""}], "hv_llct": [], "hv_ngoaingu": [], "hv_tinhoc": []}, "tab_congtac": {"ct_donvi": [{"id": "", "begin": "06/1996", "end": "10/2002", "place": "Phân viện Địa lý tại Tp.HCM thuộc Trung tân Khoa học tự nhiên và công nghệ Quốc Gia", "chucvu": "Nghiên cứu viên"}, {"id": 2, "begin": "11/2002", "end": "7/2023", "place": "Khoa Địa lý, trường Đại học Khoa học Xã hội và Nhân văn-ĐHQGHCM", "chucvu": "Trưởng Khoa, Phó Khoa, Trưởng phòng GIS"}, {"id": 3, "begin": "8/2015", "end": "4/2024", "place": "TTNC Biển, đảo và BĐKH", "chucvu": "Giám Đốc (Kiêm nhiệm)"}, {"id": 4, "begin": "08/2023", "end": "4/2024", "place": "Khoa Đô Thị", "chucvu": "Trưởng Khoa"}]}, "tab_tieusu": {"ts_cdc": [], "ts_nuocngoai": []}, "tab_khenthuong": {"kt_khen": [{"id": "1", "year": "2014", "id_chuyenmon": "01", "loai_td": "Danh hiệu Giảng viên giỏi", "id_hinhthuc": "07"}, {"id": "2", "year": "2014", "id_chuyenmon": "01", "loai_td": "Danh hiệu Lao động tiên tiến", "id_hinhthuc": "07"}, {"id": "3", "year": "2015", "id_chuyenmon": "01", "loai_td": "Danh hiệu Giảng viên giỏi", "id_hinhthuc": "07"}, {"id": "4", "year": "2015", "id_chuyenmon": "01", "loai_td": "Danh hiệu Lao động tiên tiến", "id_hinhthuc": "07"}, {"id": "5", "year": "2015", "id_chuyenmon": "01", "loai_td": "Giấy khen của Hiệu trưởng", "id_hinhthuc": "06"}, {"id": "6", "year": "2016", "id_chuyenmon": "01", "loai_td": "Danh hiệu Giảng viên giỏi", "id_hinhthuc": "07"}, {"id": "7", "year": "2016", "id_chuyenmon": "01", "loai_td": "Danh hiệu Lao động tiên tiến", "id_hinhthuc": "07"}, {"id": "8", "year": "2016", "id_chuyenmon": "01", "loai_td": "Giấy khen của Hiệu trưởng", "id_hinhthuc": "06"}, {"id": "9", "year": "2017", "id_chuyenmon": "01", "loai_td": "Danh hiệu Giảng viên giỏi", "id_hinhthuc": "07"}, {"id": "10", "year": "2017", "id_chuyenmon": "01", "loai_td": "Danh hiệu Lao động tiên tiến", "id_hinhthuc": "07"}, {"id": "11", "year": "2018", "id_chuyenmon": "01", "loai_td": "Danh hiệu Giảng viên giỏi", "id_hinhthuc": "07"}, {"id": "12", "year": "2018", "id_chuyenmon": "01", "loai_td": "Danh hiệu Lao động tiên tiến", "id_hinhthuc": "07"}, {"id": "13", "year": "2018", "id_chuyenmon": "01", "loai_td": "Giấy khen của Hiệu trưởng", "id_hinhthuc": "06"}, {"id": "14", "year": "2019", "id_chuyenmon": "01", "loai_td": "Danh hiệu Chiến sĩ thi đua cấp Trường", "id_hinhthuc": "07"}, {"id": "15", "year": "2019", "id_chuyenmon": "01", "loai_td": "Danh hiệu Giảng viên giỏi", "id_hinhthuc": "07"}, {"id": "16", "year": "2019", "id_chuyenmon": "01", "loai_td": "Danh hiệu Lao động tiên tiến", "id_hinhthuc": "07"}, {"id": "17", "year": "2020", "id_chuyenmon": "01", "loai_td": "Danh hiệu Chiến sĩ thi đua cấp Trường", "id_hinhthuc": "07"}, {"id": "18", "year": "2020", "id_chuyenmon": "01", "loai_td": "Danh hiệu Giảng viên giỏi", "id_hinhthuc": "07"}, {"id": "19", "year": "2020", "id_chuyenmon": "01", "loai_td": "Danh hiệu Lao động tiên tiến", "id_hinhthuc": "07"}, {"id": "20", "year": "2020", "id_chuyenmon": "01", "loai_td": "Giấy khen của Hiệu trưởng", "id_hinhthuc": "06"}, {"id": "21", "year": "2021", "id_chuyenmon": "01", "loai_td": "Danh hiệu Chiến sĩ thi đua cấp Trường", "id_hinhthuc": "07"}, {"id": "22", "year": "2021", "id_chuyenmon": "01", "loai_td": "Danh hiệu Lao động tiên tiến", "id_hinhthuc": "07"}, {"id": "23", "year": "2021", "id_chuyenmon": "01", "loai_td": "Giấy khen của Hiệu trưởng", "id_hinhthuc": "06"}, {"id": "24", "year": "2022", "id_chuyenmon": "01", "loai_td": "Bằng khen của Bộ trưởng Bộ Giáo dục và Đào tạo", "id_hinhthuc": "05"}, {"id": "25", "year": "2022", "id_chuyenmon": "01", "loai_td": "Danh hiệu Chiến sĩ thi đua cấp Bộ Giáo dục và Đào tạo", "id_hinhthuc": "07"}, {"id": "26", "year": "2022", "id_chuyenmon": "01", "loai_td": "Danh hiệu Chiến sĩ thi đua cấp Trường", "id_hinhthuc": "07"}, {"id": "27", "year": "2022", "id_chuyenmon": "01", "loai_td": "Danh hiệu Lao động tiên tiến", "id_hinhthuc": "07"}, {"id": "28", "year": "2022", "id_chuyenmon": "01", "loai_td": "Giấy khen của Hiệu trưởng", "id_hinhthuc": "06"}, {"id": "29", "year": "2023", "id_chuyenmon": "01", "loai_td": "Danh hiệu Lao động tiên tiến", "id_hinhthuc": "07"}, {"id": "30", "year": "2023", "id_chuyenmon": "01", "loai_td": "Giấy khen của Hiệu trưởng", "id_hinhthuc": "06"}], "kt_kyluat": []}, "tab_giacanh": {"gc_banthan": [{"id": "", "id_qh": "03", "name": "Lê Văn Bình", "year": "1937", "detail": "An Hòa, Sa Đéc, Đồng Tháp, y sĩ, nghỉ hưu, Nơi ở: 13C ấp Mới 1, Xã Tân Xuân, Hóc Môn, Tp.HCM"}, {"id": 2, "id_qh": "04", "name": "Nguyễn Thị An Mẫn", "year": "1943", "detail": "Bình Long, Bình Phước, nội trợ, Nơi ở: 13C ấp Mới 1, Xã Tân Xuân, Hóc Môn, Tp.HCM"}, {"id": 5, "id_qh": "05", "name": "Nguyễn Thị Phương Châu", "year": "1971", "detail": "Lam Sơn, Thành phố Hưng Yên, giảng viên chính, trưởng bộ môn Địa lý kinh tế phát triển vùng, Trường Đại học Khoa học Xã hội và Nhân văn-ĐHQGHCM; Nơi ở: 240 Bùi Hữu Nghĩa, Phường 02 Bình Thạnh, TPHCM"}, {"id": 6, "id_qh": "07", "name": "Lê Quốc Hoàng", "year": "2003", "detail": "An Hòa, Sa Đéc, Đồng Tháp, sinh viên Đại học Việt Đức; Nơi ở 37/53A Khu phố 4, Tân Chánh Hiệp, Quận 12, TPHCM"}, {"id": 7, "id_qh": "08", "name": "Lê Thanh Long", "year": "1961", "detail": "An Hòa, Sa Đéc, Đồng Tháp; Nơi ở: Lô 9, Cứ Xá Thanh Đa, Phường 27, Quận Bình Thạnh, nghỉ hưu"}, {"id": 8, "id_qh": "08", "name": "Lê Thanh Minh", "year": "1963", "detail": "An Hòa, Sa Đéc, Đồng Tháp; Nơi ở: 66/3 đường 185, Phước Long B, TP Thủ Đức, nghỉ hưu"}, {"id": 9, "id_qh": "08", "name": "- Lê Thanh Phúc", "year": "1966", "detail": "An Hòa, Sa Đéc, Đồng Tháp; Nơi ở: Guericke Str 44, 93053 Rengensburg, Cộng hòa Liên bang Đức, công nhân kỹ thuật BMW"}, {"id": 10, "id_qh": "09", "name": "Lê Thị Thanh Trang", "year": "1968", "detail": "An Hòa, Sa Đéc, Đồng Tháp, Nơi ở: 109/6 Bình Quới, Phường 27, Quận Bình Thạnh, Kinh doanh thuốc"}, {"id": 11, "id_qh": "10", "name": "Lê Thanh Hưng", "year": "1972", "detail": "An Hòa, Sa Đéc, Đồng Tháp, Nơi ở 13C ấp Mới 1, Xã Tân Xuân, Hóc Môn, Tp.HCM, Kinh doanh tự do"}], "gc_giadinh": [{"id": 3, "id_qh": "03", "name": "Nguyễn Văn Quyển", "year": "1932", "detail": "Lam Sơn, Thành phố Hưng Yên, hưu trí, nơi ở 240 Bùi Hữu Nghĩa, Phường 02, Quận Bình Thạnh"}, {"id": 12, "id_qh": "09", "name": "Nguyễn Thị Mai", "year": "1955", "detail": "Lam Sơn, Thành phố Hưng Yên, hưu trí, nơi ở 240 Bùi Hữu Nghĩa, Phường 02, Quận Bình Thạnh"}, {"id": 13, "id_qh": "09", "name": "Nguyễn Thị Hoa", "year": "1957", "detail": "Lam Sơn, Thành phố Hưng Yên, nội trợ, nơi ở Mỹ"}, {"id": 14, "id_qh": "08", "name": "Nguyễn Văn Tuyên", "year": "1959", "detail": "Lam Sơn, Thành phố Hưng Yên, Thợ máy, nơi ở 240 Bùi Hữu Nghĩa, Phường 02, Quận Bình Thạnh"}, {"id": 15, "id_qh": "08", "name": "Nguyễn Văn Toàn", "year": "1962", "detail": "Lam Sơn, Thành phố Hưng Yên, Công nhân, nơi ở Úc"}, {"id": 16, "id_qh": "09", "name": "Nguyễn Thị Huy", "year": "1964", "detail": "Lam Sơn, Thành phố Hưng Yên, Thợ may, nơi ở 240 Bùi Hữu Nghĩa, Phường 02, Quận Bình Thạnh"}, {"id": 17, "id_qh": "09", "name": "Nguyễn Thị Phương", "year": "1966", "detail": "Lam Sơn, Thành phố Hưng Yên, Thợ may, nơi ở Quận Tân Bình"}, {"id": 18, "id_qh": "08", "name": "Nguyễn Tấn Thành", "year": "1969", "detail": "Lam Sơn, Thành phố Hưng Yên, Công nhân, nơi ở Mỹ"}, {"id": 19, "id_qh": "09", "name": "Nguyễn Thị Ngọc Lan", "year": "1969", "detail": "Lam Sơn, Thành phố Hưng Yên, Thợ may, nơi ở 240 Bùi Hữu Nghĩa, Phường 02, Quận Bình Thạnh"}, {"id": 20, "id_qh": "10", "name": "Nguyễn Thị Phương Thảo", "year": "1974", "detail": "Lam Sơn, Thành phố Hưng Yên, Kinh doanh, nơi ở 240 Bùi Hữu Nghĩa, Phường 02, Quận Bình Thạnh"}, {"id": 21, "id_qh": "10", "name": "Nguyễn Thị Ngọc Dung", "year": "1077", "detail": "Lam Sơn, Thành phố Hưng Yên, Kinh doanh, nơi ở 240 Bùi Hữu Nghĩa, Phường 02, Quận Bình Thạnh"}], "gc_luong": [{"id": "1", "begin": "11/2002", "end": "03/2003", "maso": "13.092", "bacluong": "01", "heso": "2.34", "tienluong": "Chưa xác định"}, {"id": "2", "begin": "04/2003", "end": "09/2004", "maso": "15.111", "bacluong": "03", "heso": "2.4", "tienluong": "Chưa xác định"}, {"id": "3", "begin": "10/2004", "end": "08/2005", "maso": "15.111", "bacluong": "03", "heso": "3", "tienluong": "Chưa xác định"}, {"id": "4", "begin": "09/2005", "end": "08/2008", "maso": "15.111", "bacluong": "04", "heso": "3.33", "tienluong": "Chưa xác định"}, {"id": "5", "begin": "09/2008", "end": "01/2009", "maso": "15.111", "bacluong": "05", "heso": "3.66", "tienluong": "Chưa xác định"}, {"id": "6", "begin": "02/2009", "end": "01/2012", "maso": "15.110", "bacluong": "01", "heso": "4.4", "tienluong": "Chưa xác định"}, {"id": "7", "begin": "02/2012", "end": "01/2015", "maso": "15.110", "bacluong": "02", "heso": "4.74", "tienluong": "Chưa xác định"}, {"id": "8", "begin": "02/2015", "end": "01/2018", "maso": "15.110", "bacluong": "03", "heso": "5.08", "tienluong": "Chưa xác định"}, {"id": "9", "begin": "02/2018", "end": "01/2020", "maso": "V.07.01.02", "bacluong": "04", "heso": "5.42", "tienluong": "Chưa xác định"}, {"id": "10", "begin": "02/2020", "end": "01/2023", "maso": "V.07.01.02", "bacluong": "05", "heso": "5.76", "tienluong": "Chưa xác định"}, {"id": "11", "begin": "02/2023", "end": "04/2024", "maso": "V.07.01.02", "bacluong": "06", "heso": "6.10", "tienluong": "Chưa xác định"}], "gc_phucap": [{"id": "1", "begin": "08/2023", "end": "04/2024", "id_loai": "19", "phantram": "Không", "heso": "0.5", "hinhthuc": "Hàng tháng", "tienluong": "900000"}], "gc_taisan": [{"id": "", "loai": "6", "dientich": "173", "giay": "CH02271"}, {"id": 4, "loai": "5", "dientich": "175", "giay": "CS18591"}]}}}}