{"status": "ok", "message": "done", "result": {"bio": {"tab_canhan": {"ca_nhan": {"hovaten": "NGUYỄN THỊ ÁNH NGUYỆT", "gioitinh": "2", "ngaysinh": "09/07/1981", "id_noisinh": "79", "noisinh": "TP. Hồ Chí Minh", "id_tinh": "01", "tinh": "TP. Hà Nội", "huyen": "273", "xa": "09820", "id_tinh1": "79", "tinh1": "TP. Hồ Chí Minh", "huyen1": "765", "xa1": "26956", "duong": "117/135 Nguyễn Hữu Cảnh", "cccd": "079181031638", "ngay_cccd": "22/11/2021", "id_dantoc": "01", "dantoc": "Kinh (Việt)", "tongiao": "99", "avata": "", "avata_data_type": "", "filename": "", "type": "vc", "unitCode": "XHNV"}, "cong_tac": {"ngay": "13/10/2003", "dt": "0903042981", "email": "nguyetxhnv@hcmussh.edu.vn", "ngay_dang": "11/09/2006", "ngay_ct": "11/09/2007", "id_trinhdo": "22", "chuyenmon": "02", "id_danhhieu": "", "danhhieu": "", "hocham": "", "macb": "QSX8100494"}, "chuc_vu": {"id_chucvu": "", "chucvu": "", "congviec": "Giảng viên chính", "id_dang": "", "cv_dang": "", "id_ngach": "V.07.01.02", "ngach": "Phó giáo sư - giảng viên chính", "maso": "", "ngay_bonhiem": "", "bacluong": "02", "heso": "4.74", "ngay_huong": "01/04/2023", "pt_huong": "không", "phu_cap": "không", "ngay_phucap": ""}, "viec_lam": {"vitri": "", "maso": "", "bacluong": "", "luong": "", "ngay_huong": "", "pt_huong": "", "phu_cap": "", "ngay_phucap": ""}}, "tab_hocvan": {"hv_chuyenmon": [{"id": "", "begin": "09/1999", "end": "7/2003", "id_place": "", "place": "Trường ĐHKHXH&NV (ĐHQG TPHCM)", "id_chuyennganh": "9229013", "chuyennganh": "Lịch sử Việt Nam", "id_hinhthuc": "00", "id_vanbang": "04", "vanbang": ""}, {"id": 2, "begin": "9/2004", "end": "8/2007", "id_place": "", "place": "Trường ĐHKHXH&NV (ĐHQG TPHCM)", "id_chuyennganh": "9229013", "chuyennganh": "Lịch sử Việt Nam", "id_hinhthuc": "00", "id_vanbang": "03", "vanbang": ""}, {"id": 4, "begin": "3/2009", "end": "1/2016", "id_place": "", "place": "Trường ĐHKHXH&NV (ĐHQG TPHCM)", "id_chuyennganh": "9229013", "chuyennganh": "Lịch sử Việt Nam", "id_hinhthuc": "00", "id_vanbang": "02", "vanbang": ""}], "hv_llct": [], "hv_ngoaingu": [{"id": "", "begin": "5/2016", "end": "6/2016", "id_place": "", "place": "Đại Học Quốc gia TpHCM", "id_ngonngu": "01", "chunh_chi": "VNU", "diem": "B1.2"}, {"id": 5, "begin": "9/2007", "end": "7/2008", "id_place": "", "place": "Trường Đại học Sư phạm Quảng Tây, Trung Quốc", "id_ngonngu": "05", "chunh_chi": "Tiên tu Hán ngữ", "diem": "HSK3"}], "hv_tinhoc": [{"id": "", "begin": "5/2016", "end": "8/2016", "id_place": "", "place": "Trường ĐHKHXH&NV (Đại học Quốc gia TPHCM)", "chunh_chi": "Tin học cơ bản"}]}, "tab_congtac": {"ct_donvi": [{"id": "", "begin": "10/2003", "end": "12/2023", "place": "Khoa Lịch sử - Trường ĐHKHXH&NV (Đại học Quốc gia TpHCM)", "chucvu": "Trợ giảng"}, {"id": 2, "begin": "1/2004", "end": "5/2014", "place": "Khoa lịch sử (Trường ĐHKHXH&NV - ĐHQG TPHCM)", "chucvu": "Giảng viên"}, {"id": 3, "begin": "5/2014", "end": "12/2017", "place": "Bộ môn Lưu trữ - QTVP (Trường ĐHKHXH&NV - ĐHQG TPHCM)", "chucvu": "Giảng viên"}, {"id": 4, "begin": "12/2017", "end": "4/2021", "place": "Khoa Việt Nam học (Trường ĐHKHXH&NV - ĐHQG TPHCM)", "chucvu": "Giảng viên"}, {"id": 5, "begin": "4/2021", "end": "4/2024", "place": "Khoa Việt Nam học (Trường ĐHKHXH&NV - ĐHQG TPHCM)", "chucvu": "Giảng viên chính"}]}, "tab_tieusu": {"ts_cdc": [], "ts_nuocngoai": []}, "tab_khenthuong": {"kt_khen": [{"id": "1", "year": "2015", "id_chuyenmon": "01", "loai_td": "Danh hiệu Giảng viên giỏi", "id_hinhthuc": "07"}, {"id": "2", "year": "2015", "id_chuyenmon": "01", "loai_td": "Danh hiệu Lao động tiên tiến", "id_hinhthuc": "07"}, {"id": "3", "year": "2015", "id_chuyenmon": "01", "loai_td": "Giấy khen của Hiệu trưởng", "id_hinhthuc": "06"}, {"id": "4", "year": "2016", "id_chuyenmon": "01", "loai_td": "Danh hiệu Giảng viên giỏi", "id_hinhthuc": "07"}, {"id": "5", "year": "2016", "id_chuyenmon": "01", "loai_td": "Danh hiệu Lao động tiên tiến", "id_hinhthuc": "07"}, {"id": "6", "year": "2016", "id_chuyenmon": "01", "loai_td": "Giấy khen của Hiệu trưởng", "id_hinhthuc": "06"}, {"id": "7", "year": "2017", "id_chuyenmon": "01", "loai_td": "Danh hiệu Giảng viên giỏi", "id_hinhthuc": "07"}, {"id": "8", "year": "2017", "id_chuyenmon": "01", "loai_td": "Danh hiệu Lao động tiên tiến", "id_hinhthuc": "07"}, {"id": "9", "year": "2017", "id_chuyenmon": "01", "loai_td": "Giấy khen của Hiệu trưởng", "id_hinhthuc": "06"}, {"id": "10", "year": "2018", "id_chuyenmon": "01", "loai_td": "Danh hiệu Giảng viên giỏi", "id_hinhthuc": "07"}, {"id": "11", "year": "2018", "id_chuyenmon": "01", "loai_td": "Danh hiệu Lao động tiên tiến", "id_hinhthuc": "07"}, {"id": "12", "year": "2018", "id_chuyenmon": "01", "loai_td": "Giấy khen của Hiệu trưởng", "id_hinhthuc": "06"}, {"id": "13", "year": "2019", "id_chuyenmon": "01", "loai_td": "Danh hiệu Giảng viên giỏi", "id_hinhthuc": "07"}, {"id": "14", "year": "2019", "id_chuyenmon": "01", "loai_td": "Danh hiệu Lao động tiên tiến", "id_hinhthuc": "07"}, {"id": "15", "year": "2019", "id_chuyenmon": "01", "loai_td": "Giấy khen của Hiệu trưởng", "id_hinhthuc": "06"}, {"id": "16", "year": "2020", "id_chuyenmon": "01", "loai_td": "Danh hiệu Giảng viên giỏi", "id_hinhthuc": "07"}, {"id": "17", "year": "2020", "id_chuyenmon": "01", "loai_td": "Danh hiệu Lao động tiên tiến", "id_hinhthuc": "07"}, {"id": "18", "year": "2020", "id_chuyenmon": "01", "loai_td": "Giấy khen của Hiệu trưởng", "id_hinhthuc": "06"}, {"id": "19", "year": "2021", "id_chuyenmon": "01", "loai_td": "Danh hiệu Chiến sĩ thi đua cấp Trường", "id_hinhthuc": "07"}, {"id": "20", "year": "2021", "id_chuyenmon": "01", "loai_td": "Danh hiệu Lao động tiên tiến", "id_hinhthuc": "07"}, {"id": "21", "year": "2021", "id_chuyenmon": "01", "loai_td": "Giấy khen của Hiệu trưởng", "id_hinhthuc": "06"}, {"id": "22", "year": "2022", "id_chuyenmon": "01", "loai_td": "Bằng khen của Bộ trưởng Bộ Giáo dục và Đào tạo", "id_hinhthuc": "05"}, {"id": "23", "year": "2022", "id_chuyenmon": "01", "loai_td": "Danh hiệu Chiến sĩ thi đua cấp Trường", "id_hinhthuc": "07"}, {"id": "24", "year": "2022", "id_chuyenmon": "01", "loai_td": "Danh hiệu Lao động tiên tiến", "id_hinhthuc": "07"}, {"id": "25", "year": "2022", "id_chuyenmon": "01", "loai_td": "Giấy khen của Hiệu trưởng", "id_hinhthuc": "06"}, {"id": "26", "year": "2023", "id_chuyenmon": "01", "loai_td": "Danh hiệu Chiến sĩ thi đua cấp Bộ Giáo dục và Đào tạo", "id_hinhthuc": "07"}, {"id": "27", "year": "2023", "id_chuyenmon": "01", "loai_td": "Danh hiệu Chiến sĩ thi đua cơ sở", "id_hinhthuc": "07"}, {"id": "28", "year": "2023", "id_chuyenmon": "01", "loai_td": "Danh hiệu Lao động tiên tiến", "id_hinhthuc": "07"}, {"id": "29", "year": "2023", "id_chuyenmon": "01", "loai_td": "Giấy khen của Hiệu trưởng", "id_hinhthuc": "06"}], "kt_kyluat": []}, "tab_giacanh": {"gc_banthan": [{"id": "", "id_qh": "03", "name": "Nguyễn Văn Dụ", "year": "1946", "detail": "Xã Tân Lập, huyện Đan Phượng, Tp Hà Nội. Nghề nghiệp: Thượng tá - Nguyên Phó Hiệu trưởng Trường Cao đảng Kỹ thuật tàu Hải Quân. Đã nghỉ hưu. Địa chỉ thường trú: 117/106B Nguyễn Hữu Cảnh, f22, quận Bình Thạnh, TpHCM. Đảng viên ĐCSVN"}, {"id": 2, "id_qh": "04", "name": "Nguyễn Thị Vy", "year": "1949", "detail": "Xã Tân Lập, huyện Đan Phượng, Tp Hà Nội. Nghề nghiệp: quân nhân chuyên nghiệp XNLH Ba Son. Đã nghỉ hưu. Địa chỉ thường trú: 112 Ngô Tất Tố, f22, quận Bình Thạnh, TpHCM"}, {"id": 5, "id_qh": "09", "name": "Nguyễn Thị Kim Dung", "year": "1974", "detail": "Xã Tân Lập, huyện Đan Phượng, Tp Hà Nội. Nghề nghiệp: Chánh văn phòng. Đã nghỉ hưu. Địa chỉ thường trú: 117/106C Nguyễn Hữu Cảnh, F22, quận Bình Thạnh, TpHCM. Đảng viên ĐCSVN"}, {"id": 6, "id_qh": "09", "name": "Nguyễn Thị Mai Hương", "year": "1975", "detail": "Xã Tân Lập, huyện Đan Phượng, Tp Hà Nội. Nghề nghiệp: Giảng viên chính Trường Cao đẳng Công thương. Địa chỉ thường trú: 119/7 Trần Thị Điệu, phường Phước Long B, Quận 9. Đảng viên ĐCSVN"}, {"id": 7, "id_qh": "10", "name": "Nguyễn Như Ý", "year": "1985", "detail": "Xã Tân Lập, huyện Đan Phượng, Tp Hà Nội. Nghề nghiệp: nhân viên văn phòng Công ty phục vụ mặt đất Tân Sơn Nhất - Tiags. Địa chỉ thường trú: 117/106B Nguyễn Hữu Cảnh, f22, quận Bình Thạnh, TpHCM. Đảng viên ĐCSVN"}, {"id": 8, "id_qh": "06", "name": "Lưu Văn Quyết", "year": "1980", "detail": "Xã Nghĩa Lạc, huyện Nghĩa Hưng, Tp Nam Định. Nghề nghiệp: giảng viên cao cấp Trường ĐHKHXH&NV (ĐHQG TPHCM). Địa chỉ thường trú: 117/135 Nguyễn Hữu Cảnh, f22, quận Bình Thạnh. Đảng viên ĐCSVN"}, {"id": 9, "id_qh": "07", "name": "Lưu Minh Lam", "year": "2010", "detail": "Xã Nghĩa Lạc, huyện Nghĩa Hưng, Tp Nam Định. Nghề nghiệp: học sinh Trường THCS&PTTH Vinschool. Địa chỉ thường trú: 117/135 Nguyễn Hữu Cảnh, f22, quận Bình Thạnh, TpHCM."}, {"id": 10, "id_qh": "07", "name": "Lưu Quỳnh Lam", "year": "2017", "detail": "Xã Nghĩa Lạc, huyện Nghĩa Hưng, Tp Nam Định. Nghề nghiệp: học sinh tiểu học - Trường tiểu học Vinschool. Địa chỉ thường trú: 117/135 Nguyễn Hữu Cảnh, F22, quận Bình Thạnh, TpHCM."}], "gc_giadinh": [{"id": 3, "id_qh": "03", "name": "Lưu Văn Phẩm", "year": "1933", "detail": "Xã Nghĩa Lạc, huyện Nghĩa Hưng, tỉnh Nam Định. Nghề nghiệp: nông dân. Đã mất. Không làm gì cho đế quốc, thực dân."}, {"id": 11, "id_qh": "04", "name": "Lưu Thị Phẩm (Hoàng Thị Sáng)", "year": "1938", "detail": "Xã Nghĩa Lạc, huyện Nghĩa Hưng, tỉnh Nam Định. Nghề nghiệp: nông dân. Cư trú tại địa phương. Không làm gì cho đế quốc và thực dân"}, {"id": 12, "id_qh": "08", "name": "Lưu Thành Quát", "year": "1957", "detail": "Xã Nghĩa Lạc, huyện Nghĩa Hưng, tỉnh Nam Định. Hiện nay sinh sống cùng con ở Thành phố Thủ Đức."}, {"id": 13, "id_qh": "08", "name": "Lưu Quang Đạt", "year": "1961", "detail": "Xã Nghĩa Lạc, huyện Nghĩa Hưng, tỉnh Nam Định. Từng làm tiểu đội trưởng. Hiện nay làm ngư nghiệp tại huyện Phú Tân, Cà Mau."}, {"id": 14, "id_qh": "09", "name": "Lưu Thị Tươi", "year": "1963", "detail": "Xã Nghĩa Lạc, huyện Nghĩa Hưng, tỉnh  Nam Định. Hiện làm nông ở địa phương."}, {"id": 15, "id_qh": "09", "name": "Lưu Thị Tốt", "year": "1967", "detail": "Xã Nghĩa Lạc, huyện Nghĩa Hưng, tỉnh Nam Định. Hiện sống và làm chăn nuôi ở xã Bầu Cạn, Long Thành, Đồng Nai."}, {"id": 16, "id_qh": "09", "name": "Lưu Thị Xuân", "year": "1970", "detail": "Xã Nghĩa Lạc, huyện Nghĩa Hưng, tỉnh Nam Định. Hiện sống và làm nông tại địa phương."}, {"id": 17, "id_qh": "09", "name": "Lưu Thị Huế", "year": "1973", "detail": "Xã Nghĩa Lạc, huyện Nghĩa Hưng, tỉnh Nam Định. Hiện sống và làm nông ở huyện Nghĩa Phú, tỉnh Nam Định."}, {"id": 18, "id_qh": "08", "name": "Lưu Văn Đỉnh", "year": "1977", "detail": "Xã Nghĩa Lạc, huyện Nghĩa Hưng, tỉnh Nam Định. Hiện sống và làm nông ở địa phương."}], "gc_luong": [{"id": "1", "begin": "01/2004", "end": "03/2004", "maso": "15.111", "bacluong": "01", "heso": "1.92", "tienluong": "Chưa xác định"}, {"id": "2", "begin": "04/2004", "end": "09/2004", "maso": "15.111", "bacluong": "01", "heso": "1.92", "tienluong": "Chưa xác định"}, {"id": "3", "begin": "10/2004", "end": "09/2007", "maso": "15.111", "bacluong": "01", "heso": "2.34", "tienluong": "Chưa xác định"}, {"id": "4", "begin": "10/2007", "end": "09/2010", "maso": "15.111", "bacluong": "02", "heso": "2.67", "tienluong": "Chưa xác định"}, {"id": "5", "begin": "10/2010", "end": "09/2013", "maso": "15.111", "bacluong": "03", "heso": "3", "tienluong": "Chưa xác định"}, {"id": "6", "begin": "10/2013", "end": "09/2016", "maso": "15.111", "bacluong": "04", "heso": "3.33", "tienluong": "Chưa xác định"}, {"id": "7", "begin": "10/2016", "end": "09/2019", "maso": "V.07.01.03", "bacluong": "05", "heso": "3.66", "tienluong": "Chưa xác định"}, {"id": "8", "begin": "10/2019", "end": "03/2021", "maso": "V.07.01.03", "bacluong": "06", "heso": "3.99", "tienluong": "Chưa xác định"}, {"id": "9", "begin": "04/2021", "end": "03/2023", "maso": "V.07.01.02", "bacluong": "01", "heso": "4.4", "tienluong": "Chưa xác định"}, {"id": "10", "begin": "04/2023", "end": "04/2024", "maso": "V.07.01.02", "bacluong": "02", "heso": "4.74", "tienluong": "Chưa xác định"}], "gc_phucap": [], "gc_taisan": [{"id": "", "loai": "5", "dientich": "104", "giay": "GCN04435 do UBND quận Bình Thạnh cấp 26/9/2018"}, {"id": 4, "loai": "10", "dientich": "61", "giay": "CH04797 do UBND quận 9 cấp ngày 23/9/2019"}]}}}}