{"status": "ok", "message": "done", "result": {"bio": {"tab_canhan": {"ca_nhan": {"hovaten": "ĐẶNG NGUYỄN THIÊN HƯƠNG", "gioitinh": "2", "ngaysinh": "06/09/1981", "id_noisinh": "79", "noisinh": "TP. Hồ Chí Minh", "id_tinh": "36", "tinh": "Nam Định", "huyen": "356", "xa": "13654", "id_tinh1": "79", "tinh1": "TP. Hồ Chí Minh", "huyen1": "766", "xa1": "26980", "duong": "71/88/35 Nguyễn Bặc", "cccd": "079181020388", "ngay_cccd": "17/08/2021", "id_dantoc": "01", "dantoc": "Kinh (Việt)", "tongiao": "99", "avata": "", "avata_data_type": "", "filename": "", "type": "vc", "unitCode": "XHNV"}, "cong_tac": {"ngay": "01/04/2009", "dt": "0903040299", "email": "thienhuong_fus@hcmussh.edu.vn", "ngay_dang": "", "ngay_ct": "", "id_trinhdo": "22", "chuyenmon": "03", "id_danhhieu": "", "danhhieu": "", "hocham": "", "macb": "QSX8100286"}, "chuc_vu": {"id_chucvu": "", "chucvu": "", "congviec": "Giảng viên", "id_dang": "", "cv_dang": "", "id_ngach": "V.07.01.03", "ngach": "Giảng viên", "maso": "", "ngay_bonhiem": "01/02/2010", "bacluong": "06", "heso": "3.99", "ngay_huong": "01/04/2022", "pt_huong": "không", "phu_cap": "không", "ngay_phucap": ""}, "viec_lam": {"vitri": "", "maso": "", "bacluong": "", "luong": "", "ngay_huong": "", "pt_huong": "", "phu_cap": "", "ngay_phucap": ""}}, "tab_hocvan": {"hv_chuyenmon": [{"id": 2, "begin": "09/1999", "end": "09/2004", "id_place": "ĐH.VI.97.1", "place": "ĐHQG.HCM - Trường Đại Học Bách Khoa", "id_chuyennganh": "7510406", "chuyennganh": "Công nghệ kỹ thuật môi trường", "id_hinhthuc": "00", "id_vanbang": "05", "vanbang": ""}, {"id": 3, "begin": "09/2005", "end": "09/2008", "id_place": "", "place": "Viện Môi trường và tài nguyên ĐHQG.HCM - Trường Đại Học Bách Khoa", "id_chuyennganh": "", "chuyennganh": "Sử dụng và bảo vệ tài nguyên môi trường", "id_hinhthuc": "00", "id_vanbang": "03", "vanbang": ""}], "hv_llct": [], "hv_ngoaingu": [{"id": 5, "begin": "02/2021", "end": "02/2023", "id_place": "", "place": "Tự đào tạo", "id_ngonngu": "01", "chunh_chi": "IELTS", "diem": "6.5"}], "hv_tinhoc": []}, "tab_congtac": {"ct_donvi": [{"id": 2, "begin": "09/2004", "end": "05/2007", "place": "Cty TNHH Comin Vietnam", "chucvu": "kỹ thuật viên"}, {"id": 3, "begin": "09/2009", "end": "07/2023", "place": "ĐHQG.HCM Trường Đại học Khoa học Xã hội và Nhân văn", "chucvu": "Giảng viên"}]}, "tab_tieusu": {"ts_cdc": [], "ts_nuocngoai": []}, "tab_khenthuong": {"kt_khen": [{"id": "1", "year": "2015", "id_chuyenmon": "01", "loai_td": "Danh hiệu Chiến sĩ thi đua cấp Trường", "id_hinhthuc": "07"}, {"id": "2", "year": "2015", "id_chuyenmon": "01", "loai_td": "Danh hiệu Giảng viên giỏi", "id_hinhthuc": "07"}, {"id": "3", "year": "2015", "id_chuyenmon": "01", "loai_td": "Danh hiệu Lao động tiên tiến", "id_hinhthuc": "07"}, {"id": "4", "year": "2015", "id_chuyenmon": "01", "loai_td": "Giấy khen của Hiệu trưởng", "id_hinhthuc": "06"}, {"id": "5", "year": "2021", "id_chuyenmon": "01", "loai_td": "Danh hiệu Lao động tiên tiến", "id_hinhthuc": "07"}, {"id": "6", "year": "2021", "id_chuyenmon": "01", "loai_td": "Giấy khen của Hiệu trưởng", "id_hinhthuc": "06"}, {"id": "7", "year": "2022", "id_chuyenmon": "01", "loai_td": "Danh hiệu Lao động tiên tiến", "id_hinhthuc": "07"}, {"id": "8", "year": "2022", "id_chuyenmon": "01", "loai_td": "Giấy khen của Hiệu trưởng", "id_hinhthuc": "06"}, {"id": "9", "year": "2023", "id_chuyenmon": "01", "loai_td": "Danh hiệu Lao động tiên tiến", "id_hinhthuc": "07"}, {"id": "10", "year": "2023", "id_chuyenmon": "01", "loai_td": "Giấy khen của Hiệu trưởng", "id_hinhthuc": "06"}], "kt_kyluat": []}, "tab_giacanh": {"gc_banthan": [{"id": "", "id_qh": "03", "name": "Đặng Quốc Bảo", "year": "1953", "detail": "Nam Định, Hưu trí"}, {"id": 2, "id_qh": "04", "name": "Nguyễn Thị Lập", "year": "1957", "detail": "Hà Nam, Hưu trí"}], "gc_giadinh": [], "gc_luong": [{"id": "1", "begin": "06/2009", "end": "03/2010", "maso": "15.111", "bacluong": "02", "heso": "2.67 (85%)", "tienluong": "Chưa xác định"}, {"id": "2", "begin": "04/2010", "end": "03/2013", "maso": "15.111", "bacluong": "02", "heso": "2.67", "tienluong": "Chưa xác định"}, {"id": "3", "begin": "04/2013", "end": "03/2016", "maso": "15.111", "bacluong": "03", "heso": "3", "tienluong": "Chưa xác định"}, {"id": "4", "begin": "04/2016", "end": "03/2019", "maso": "V.07.01.03", "bacluong": "04", "heso": "3.33", "tienluong": "Chưa xác định"}, {"id": "5", "begin": "04/2019", "end": "03/2022", "maso": "V.07.01.03", "bacluong": "05", "heso": "3.66", "tienluong": "Chưa xác định"}, {"id": "6", "begin": "04/2022", "end": "04/2024", "maso": "V.07.01.03", "bacluong": "06", "heso": "3.99", "tienluong": "Chưa xác định"}], "gc_phucap": [], "gc_taisan": [{"id": 8, "loai": "00", "dientich": "", "giay": ""}]}}}}