[
    {"id": "7140101", "value": "[7140101] - Giáo dục học"},
    {"id": "7140102", "value": "[7140102] - Khoa học giáo dục"},
    {"id": "7140103", "value": "[7140103] - Công nghệ giáo dục"},
    {"id": "7140114", "value": "[7140114] - Quản lý giáo dục"},
    {"id": "7140115", "value": "[7140115] - Công nghệ giáo dục"},
    {"id": "7140116", "value": "[7140116] - Quản trị công nghệ giáo dục"},
    {"id": "7140117", "value": "[7140117] - Quản trị trường học"},
    {"id": "7140201", "value": "[7140201] - Giáo dục Mầm non"},
    {"id": "7140202", "value": "[7140202] - Giáo dục Tiểu học"},
    {"id": "7140203", "value": "[7140203] - Giáo dục Đặc biệt"},
    {"id": "7140204", "value": "[7140204] - Giáo dục Công dân"},
    {"id": "7140205", "value": "[7140205] - Giáo dục Chính trị"},
    {"id": "7140206", "value": "[7140206] - Giáo dục Thể chất"},
    {"id": "7140207", "value": "[7140207] - Huấn luyện thể thao"},
    {"id": "7140208", "value": "[7140208] - Giáo dục Quốc phòng - An ninh"},
    {"id": "7140209", "value": "[7140209] - Sư phạm Toán học"},
    {"id": "7140210", "value": "[7140210] - Sư phạm Tin học"},
    {"id": "7140211", "value": "[7140211] - Sư phạm Vật lý"},
    {"id": "7140212", "value": "[7140212] - Sư phạm Hoá học"},
    {"id": "7140213", "value": "[7140213] - Sư phạm Sinh học"},
    {"id": "7140214", "value": "[7140214] - Sư phạm Kỹ thuật công nghiệp"},
    {"id": "7140215", "value": "[7140215] - Sư phạm Kỹ thuật nông nghiệp"},
    {"id": "7140217", "value": "[7140217] - Sư phạm Ngữ văn"},
    {"id": "7140218", "value": "[7140218] - Sư phạm Lịch sử"},
    {"id": "7140219", "value": "[7140219] - Sư phạm Địa lý"},
    {"id": "7140221", "value": "[7140221] - Sư phạm Âm nhạc"},
    {"id": "7140222", "value": "[7140222] - Sư phạm Mỹ thuật"},
    {"id": "7140223", "value": "[7140223] - Sư phạm Tiếng Bana"},
    {"id": "7140224", "value": "[7140224] - Sư phạm Tiếng Êđê"},
    {"id": "7140225", "value": "[7140225] - Sư phạm Tiếng Jrai"},
    {"id": "7140226", "value": "[7140226] - Sư phạm Tiếng Khmer"},
    {"id": "7140227", "value": "[7140227] - Sư phạm Tiếng H`mong"},
    {"id": "7140228", "value": "[7140228] - Sư phạm Tiếng Chăm"},
    {"id": "7140229", "value": "[7140229] - Sư phạm Tiếng M`nông"},
    {"id": "7140230", "value": "[7140230] - Sư phạm Tiếng Xê đăng"},
    {"id": "7140231", "value": "[7140231] - Sư phạm Tiếng Anh"},
    {"id": "7140232", "value": "[7140232] - Sư phạm Tiếng Nga"},
    {"id": "7140233", "value": "[7140233] - Sư phạm Tiếng Pháp"},
    {"id": "7140234", "value": "[7140234] - Sư phạm Tiếng Trung Quốc"},
    {"id": "7140235", "value": "[7140235] - Sư phạm Tiếng Đức"},
    {"id": "7140236", "value": "[7140236] - Sư phạm Tiếng Nhật"},
    {"id": "7140237", "value": "[7140237] - Sư phạm Tiếng Hàn Quốc"},
    {"id": "7140245", "value": "[7140245] - Sư phạm nghệ thuật"},
    {"id": "7140246", "value": "[7140246] - Sư phạm công nghệ"},
    {"id": "7140247", "value": "[7140247] - Sư phạm khoa học tự nhiên"},
    {"id": "7140248", "value": "[7140248] - Giáo dục pháp luật"},
    {"id": "7140249", "value": "[7140249] - Sư phạm Lịch sử - Địa lí"},
    {"id": "7140250", "value": "[7140250] - Sư phạm Tin học và Công nghệ tiểu học"},
    {"id": "7149001", "value": "[7149001] - Kinh tế giáo dục"},
    {"id": "7210101", "value": "[7210101] - Lý luận, lịch sử và phê bình mỹ thuật"},
    {"id": "7210103", "value": "[7210103] - Hội hoạ"},
    {"id": "7210104", "value": "[7210104] - Đồ hoạ"},
    {"id": "7210105", "value": "[7210105] - Điêu khắc"},
    {"id": "7210107", "value": "[7210107] - Gốm"},
    {"id": "7210110", "value": "[7210110] - Mỹ thuật đô thị"},
    {"id": "7210201", "value": "[7210201] - Âm nhạc học"},
    {"id": "7210203", "value": "[7210203] - Sáng tác âm nhạc"},
    {"id": "7210204", "value": "[7210204] - Chỉ huy âm nhạc"},
    {"id": "7210205", "value": "[7210205] - Thanh nhạc"},
    {"id": "7210207", "value": "[7210207] - Biểu diễn nhạc cụ phương tây"},
    {"id": "7210208", "value": "[7210208] - Piano"},
    {"id": "7210209", "value": "[7210209] - Nhạc Jazz"},
    {"id": "7210210", "value": "[7210210] - Biểu diễn nhạc cụ truyền thống"},
    {"id": "7210221", "value": "[7210221] - Lý luận, lịch sử và phê bình sân khấu"},
    {"id": "7210225", "value": "[7210225] - Biên kịch sân khấu"},
    {"id": "7210226", "value": "[7210226] - Diễn viên sân khấu kịch hát"},
    {"id": "7210227", "value": "[7210227] - Đạo diễn sân khấu"},
    {"id": "7210231", "value": "[7210231] - Lý luận, lịch sử và phê bình điện ảnh, truyền hình"},
    {"id": "7210233", "value": "[7210233] - Biên kịch điện ảnh, truyền hình"},
    {"id": "7210234", "value": "[7210234] - Diễn viên kịch, điện ảnh - truyền hình"},
    {"id": "7210235", "value": "[7210235] - Đạo diễn điện ảnh, truyền hình"},
    {"id": "7210236", "value": "[7210236] - Quay phim"},
    {"id": "7210241", "value": "[7210241] - Lý luận, lịch sử và phê bình múa"},
    {"id": "7210242", "value": "[7210242] - Diễn viên múa"},
    {"id": "7210243", "value": "[7210243] - Biên đạo múa"},
    {"id": "7210244", "value": "[7210244] - Huấn luyện múa"},
    {"id": "7210301", "value": "[7210301] - Nhiếp ảnh"},
    {"id": "7210302", "value": "[7210302] - Công nghệ điện ảnh, truyền hình"},
    {"id": "7210303", "value": "[7210303] - Thiết kế âm thanh, ánh sáng"},
    {"id": "7210304", "value": "[7210304] - Phim"},
    {"id": "7210402", "value": "[7210402] - Thiết kế công nghiệp"},
    {"id": "7210403", "value": "[7210403] - Thiết kế đồ họa"},
    {"id": "7210404", "value": "[7210404] - Thiết kế thời trang"},
    {"id": "7210405", "value": "[7210405] - Âm nhạc"},
    {"id": "7210406", "value": "[7210406] - Thiết kế mỹ thuật sân khấu, điện ảnh"},
    {"id": "7210407", "value": "[7210407] - Thiết kế kỹ thuật số"},
    {"id": "7210408", "value": "[7210408] - Nghệ thuật số"},
    {"id": "7210409", "value": "[7210409] - Thiết kế Mỹ thuật số"},
    {"id": "7220101", "value": "[7220101] - Tiếng Việt và văn hoá Việt Nam"},
    {"id": "7220104", "value": "[7220104] - Hán Nôm"},
    {"id": "7220105", "value": "[7220105] - Ngôn ngữ Jrai"},
    {"id": "7220106", "value": "[7220106] - Ngôn ngữ Khmer"},
    {"id": "7220107", "value": "[7220107] - Ngôn ngữ H`mong"},
    {"id": "7220108", "value": "[7220108] - Ngôn ngữ Chăm"},
    {"id": "7220110", "value": "[7220110] - Sáng tác văn học"},
    {"id": "7220112", "value": "[7220112] - Văn hoá các dân tộc thiểu số Việt Nam"},
    {"id": "7220201", "value": "[7220201] - Ngôn ngữ Anh"},
    {"id": "7220202", "value": "[7220202] - Ngôn ngữ Nga"},
    {"id": "7220203", "value": "[7220203] - Ngôn ngữ Pháp"},
    {"id": "7220204", "value": "[7220204] - Ngôn ngữ Trung Quốc"},
    {"id": "7220205", "value": "[7220205] - Ngôn ngữ Đức"},
    {"id": "7220206", "value": "[7220206] - Ngôn ngữ Tây Ban Nha"},
    {"id": "7220207", "value": "[7220207] - Ngôn ngữ Bồ Đào Nha"},
    {"id": "7220208", "value": "[7220208] - Ngôn ngữ Italia"},
    {"id": "7220209", "value": "[7220209] - Ngôn ngữ Nhật"},
    {"id": "7220210", "value": "[7220210] - Ngôn ngữ Hàn Quốc"},
    {"id": "7220211", "value": "[7220211] - Ngôn ngữ Ảrập"},
    {"id": "7220212QTD", "value": "[7220212QTD] - Văn hóa và truyền thông xuyên quốc gia"},
    {"id": "7220214", "value": "[7220214] - Ngôn ngữ Thái Lan"},
    {"id": "7229001", "value": "[7229001] - Triết học"},
    {"id": "7229008", "value": "[7229008] - Chủ nghĩa xã hội khoa học"},
    {"id": "7229009", "value": "[7229009] - Tôn giáo học"},
    {"id": "7229010", "value": "[7229010] - Lịch sử"},
    {"id": "7229020", "value": "[7229020] - Ngôn ngữ học"},
    {"id": "7229030", "value": "[7229030] - Văn học"},
    {"id": "7229040", "value": "[7229040] - Văn hoá học"},
    {"id": "7229042", "value": "[7229042] - Quản lý văn hoá"},
    {"id": "7229045", "value": "[7229045] - Gia đình học"},
    {"id": "7310101", "value": "[7310101] - Kinh tế"},
    {"id": "7310102", "value": "[7310102] - Kinh tế chính trị"},
    {"id": "7310104", "value": "[7310104] - Kinh tế đầu tư"},
    {"id": "7310105", "value": "[7310105] - Kinh tế phát triển"},
    {"id": "7310106", "value": "[7310106] - Kinh tế quốc tế"},
    {"id": "7310107", "value": "[7310107] - Thống kê kinh tế"},
    {"id": "7310108", "value": "[7310108] - Toán kinh tế"},
    {"id": "7310109", "value": "[7310109] - Kinh tế số"},
    {"id": "7310110", "value": "[7310110] - Quản lý kinh tế"},
    {"id": "7310111", "value": "[7310111] - Nghiên cứu phát triển"},
    {"id": "7310201", "value": "[7310201] - Chính trị học"},
    {"id": "7310202", "value": "[7310202] - Xây dựng Đảng và chính quyền nhà nước"},
    {"id": "7310205", "value": "[7310205] - Quản lý nhà nước"},
    {"id": "7310206", "value": "[7310206] - Quan hệ quốc tế"},
    {"id": "7310301", "value": "[7310301] - Xã hội học"},
    {"id": "7310302", "value": "[7310302] - Nhân học"},
    {"id": "7310401", "value": "[7310401] - Tâm lý học"},
    {"id": "7310402", "value": "[7310402] - Tham vấn học đường"},
    {"id": "7310403", "value": "[7310403] - Tâm lý học giáo dục"},
    {"id": "7310501", "value": "[7310501] - Địa lý học"},
    {"id": "7310601", "value": "[7310601] - Quốc tế học"},
    {"id": "7310602", "value": "[7310602] - Châu Á học"},
    {"id": "7310607", "value": "[7310607] - Thái Bình Dương học"},
    {"id": "7310608", "value": "[7310608] - Đông phương học"},
    {"id": "7310612", "value": "[7310612] - Trung Quốc học"},
    {"id": "7310613", "value": "[7310613] - Nhật Bản học"},
    {"id": "7310614", "value": "[7310614] - Hàn Quốc học"},
    {"id": "7310620", "value": "[7310620] - Đông Nam Á học"},
    {"id": "7310630", "value": "[7310630] - Việt Nam học"},
    {"id": "7320101", "value": "[7320101] - Báo chí"},
    {"id": "7320104", "value": "[7320104] - Truyền thông đa phương tiện"},
    {"id": "7320105", "value": "[7320105] - Truyền thông đại chúng"},
    {"id": "7320106", "value": "[7320106] - Công nghệ truyền thông"},
    {"id": "7320107", "value": "[7320107] - Truyền thông quốc tế"},
    {"id": "7320108", "value": "[7320108] - Quan hệ công chúng"},
    {"id": "7320109", "value": "[7320109] - Truyền thông doanh nghiệp"},
    {"id": "7320110", "value": "[7320110] - Quảng cáo"},
    {"id": "7320111", "value": "[7320111] - Truyền thông số"},
    {"id": "7320201", "value": "[7320201] - Thông tin - thư viện"},
    {"id": "7320205", "value": "[7320205] - Quản lý thông tin"},
    {"id": "7320303", "value": "[7320303] - Lưu trữ học"},
    {"id": "7320305", "value": "[7320305] - Bảo tàng học"},
    {"id": "7320401", "value": "[7320401] - Xuất bản"},
    {"id": "7320402", "value": "[7320402] - Kinh doanh xuất bản phẩm"},
    {"id": "7329001", "value": "[7329001] - Công nghệ đa phương tiện"},
    {"id": "7340101", "value": "[7340101] - Quản trị kinh doanh"},
    {"id": "7340102", "value": "[7340102] - Quản trị - Luật"},
    {"id": "7340108", "value": "[7340108] - Quản lý"},
    {"id": "7340114", "value": "[7340114] - Digital Marketing"},
    {"id": "7340115", "value": "[7340115] - Marketing"},
    {"id": "7340116", "value": "[7340116] - Bất động sản"},
    {"id": "7340120", "value": "[7340120] - Kinh doanh quốc tế"},
    {"id": "7340121", "value": "[7340121] - Kinh doanh thương mại"},
    {"id": "7340122", "value": "[7340122] - Thương mại điện tử"},
    {"id": "7340123", "value": "[7340123] - Kinh doanh thời trang và dệt may"},
    {"id": "7340124", "value": "[7340124] - Quản trị và Kinh doanh quốc tế"},
    {"id": "7340125", "value": "[7340125] - Phân tích dữ liệu kinh doanh"},
    {"id": "7340129", "value": "[7340129] - Quản trị kinh doanh thực phầm"},
    {"id": "7340201", "value": "[7340201] - Tài chính - Ngân hàng"},
    {"id": "7340202", "value": "[7340202] - Tài chính và Kế toán"},
    {"id": "7340204", "value": "[7340204] - Bảo hiểm"},
    {"id": "7340205", "value": "[7340205] - Công nghệ tài chính"},
    {"id": "7340206", "value": "[7340206] - Tài chính quốc tế"},
    {"id": "7340207", "value": "[7340207] - Bảo hiểm - tài chính"},
    {"id": "7340301", "value": "[7340301] - Kế toán"},
    {"id": "7340302", "value": "[7340302] - Kiểm toán"},
    {"id": "7340303", "value": "[7340303] - Kế toán, Phân tích và Kiểm toán"},
    {"id": "7340401", "value": "[7340401] - Khoa học quản lý"},
    {"id": "7340403", "value": "[7340403] - Quản lý công"},
    {"id": "7340404", "value": "[7340404] - Quản trị nhân lực"},
    {"id": "7340405", "value": "[7340405] - Hệ thống thông tin quản lý"},
    {"id": "7340406", "value": "[7340406] - Quản trị văn phòng"},
    {"id": "7340408", "value": "[7340408] - Quan hệ lao động"},
    {"id": "7340409", "value": "[7340409] - Quản lý dự án"},
    {"id": "7340410", "value": "[7340410] - Quản trị công nghệ truyền thông"},
    {"id": "7340411", "value": "[7340411] - Quản lý và phát triển nguồn nhân lực"},
    {"id": "7340412", "value": "[7340412] - Quản trị sự kiện"},
    {"id": "7340418", "value": "[7340418] - Quản lý và phát triển du lịch"},
    {"id": "7340420", "value": "[7340420] - Khoa học dữ liệu và phân tích kinh doanh"},
    {"id": "7349001", "value": "[7349001] - Quản trị thương hiệu"},
    {"id": "7349002", "value": "[7349002] - Quản lý giải trí và sự kiện"},
    {"id": "7380101", "value": "[7380101] - Luật"},
    {"id": "7380102", "value": "[7380102] - Luật hiến pháp và luật hành chính"},
    {"id": "7380103", "value": "[7380103] - Luật dân sự và tố tụng dân sự"},
    {"id": "7380104", "value": "[7380104] - Luật hình sự và tố tụng hình sự"},
    {"id": "7380107", "value": "[7380107] - Luật kinh tế"},
    {"id": "7380108", "value": "[7380108] - Luật quốc tế"},
    {"id": "7380109", "value": "[7380109] - Luật Thương mại Quốc tế"},
    {"id": "7380110", "value": "[7380110] - Luật Kinh doanh"},
    {"id": "7420101", "value": "[7420101] - Sinh học"},
    {"id": "7420201", "value": "[7420201] - Công nghệ sinh học"},
    {"id": "7420202", "value": "[7420202] - Kỹ thuật sinh học"},
    {"id": "7420203", "value": "[7420203] - Sinh học ứng dụng"},
    {"id": "7420204", "value": "[7420204] - Khoa học Y Sinh"},
    {"id": "7420205", "value": "[7420205] - Công nghệ sinh học y dược"},
    {"id": "7420207", "value": "[7420207] - Công nghệ thẩm mỹ"},
    {"id": "7420215", "value": "[7420215] - Công nghệ sinh dược"},
    {"id": "7440101", "value": "[7440101] - Thiên văn học"},
    {"id": "7440102", "value": "[7440102] - Vật lý học"},
    {"id": "7440106", "value": "[7440106] - Vật lý nguyên tử và hạt nhân"},
    {"id": "7440107", "value": "[7440107] - Công nghệ vật lý điện tử tin học"},
    {"id": "7440110", "value": "[7440110] - Cơ học"},
    {"id": "7440112", "value": "[7440112] - Hoá học"},
    {"id": "7440122", "value": "[7440122] - Khoa học vật liệu"},
    {"id": "7440201", "value": "[7440201] - Địa chất học"},
    {"id": "7440212", "value": "[7440212] - Bản đồ học"},
    {"id": "7440217", "value": "[7440217] - Địa lý tự nhiên"},
    {"id": "7440222", "value": "[7440222] - Khí tượng và khí hậu học"},
    {"id": "7440224", "value": "[7440224] - Thuỷ văn học"},
    {"id": "7440225", "value": "[7440225] - Tài nguyên và môi trường nước"},
    {"id": "7440228", "value": "[7440228] - Hải dương học"},
    {"id": "7440229", "value": "[7440229] - Quản lý và phân tích dữ liệu khoa học "},
    {"id": "7440230", "value": "[7440230] - Khoa học thông tin địa không gian"},
    {"id": "7440298", "value": "[7440298] - Biến đổi khí hậu và phát triển bền vững"},
    {"id": "7440299", "value": "[7440299] - Khí tượng thủy văn biển"},
    {"id": "7440301", "value": "[7440301] - Khoa học môi trường"},
    {"id": "7460101", "value": "[7460101] - Toán học"},
    {"id": "7460107", "value": "[7460107] - Khoa học tính toán"},
    {"id": "7460108", "value": "[7460108] - Khoa học dữ liệu"},
    {"id": "7460112", "value": "[7460112] - Toán ứng dụng"},
    {"id": "7460115", "value": "[7460115] - Toán cơ"},
    {"id": "7460117", "value": "[7460117] - Toán tin"},
    {"id": "7460201", "value": "[7460201] - Thống kê"},
    {"id": "7480101", "value": "[7480101] - Khoa học máy tính"},
    {"id": "7480102", "value": "[7480102] - Mạng máy tính và truyền thông dữ liệu"},
    {"id": "7480103", "value": "[7480103] - Kỹ thuật phần mềm"},
    {"id": "7480104", "value": "[7480104] - Hệ thống thông tin"},
    {"id": "7480106", "value": "[7480106] - Kỹ thuật máy tính"},
    {"id": "7480107", "value": "[7480107] - Trí tuệ nhân tạo"},
    {"id": "7480108", "value": "[7480108] - Công nghệ kỹ thuật máy tính"},
    {"id": "7480111", "value": "[7480111] - Tin học và kỹ thuật máy tính"},
    {"id": "7480112", "value": "[7480112] - Khoa học dữ liệu và trí tuệ nhân tạo"},
    {"id": "7480113", "value": "[7480113] - Khoa học máy tính và thông tin"},
    {"id": "7480118", "value": "[7480118] - Hệ thống nhúng và IoT"},
    {"id": "7480201", "value": "[7480201] - Công nghệ thông tin"},
    {"id": "7480202", "value": "[7480202] - An toàn thông tin"},
    {"id": "7480203", "value": "[7480203] - Kỹ thuật dữ liệu"},
    {"id": "7480204", "value": "[7480204] - Khoa học và Kỹ thuật Máy tính"},
    {"id": "7480205", "value": "[7480205] - Trí tuệ nhân tạo và Khoa học dữ liệu"},
    {"id": "7480206", "value": "[7480206] - Địa tin học"},
    {"id": "7480207", "value": "[7480207] - Trí tuệ nhân tạo"},
    {"id": "7480209", "value": "[7480209] - Công nghệ tài chính và kinh doanh số"},
    {"id": "7480210", "value": "[7480210] - Công nghệ thông tin ứng dụng"},
    {"id": "7480298", "value": "[7480298] - Khoa học dữ liệu"},
    {"id": "7510101", "value": "[7510101] - Công nghệ kỹ thuật kiến trúc"},
    {"id": "7510102", "value": "[7510102] - Công nghệ kỹ thuật công trình xây dựng"},
    {"id": "7510103", "value": "[7510103] - Công nghệ kỹ thuật xây dựng"},
    {"id": "7510104", "value": "[7510104] - Công nghệ kỹ thuật giao thông"},
    {"id": "7510105", "value": "[7510105] - Công nghệ kỹ thuật vật liệu xây dựng"},
    {"id": "7510106", "value": "[7510106] - Hệ thống kỹ thuật công trình xây dựng"},
    {"id": "7510201", "value": "[7510201] - Công nghệ kỹ thuật cơ khí"},
    {"id": "7510202", "value": "[7510202] - Công nghệ chế tạo máy"},
    {"id": "7510203", "value": "[7510203] - Công nghệ kỹ thuật cơ - điện tử"},
    {"id": "7510205", "value": "[7510205] - Công nghệ kỹ thuật ô tô"},
    {"id": "7510206", "value": "[7510206] - Công nghệ kỹ thuật nhiệt"},
    {"id": "7510207", "value": "[7510207] - Công nghệ kỹ thuật tàu thủy"},
    {"id": "7510208", "value": "[7510208] - Năng lượng tái tạo"},
    {"id": "7510209", "value": "[7510209] - Robot và trí tuệ nhân tạo"},
    {"id": "7510210", "value": "[7510210] - Điện lạnh và điều hòa không khí"},
    {"id": "7510211", "value": "[7510211] - Bảo dưỡng công nghiệp"},
    {"id": "7510212", "value": "[7510212] - Công nghệ ô tô và giao thông thông minh"},
    {"id": "7510301", "value": "[7510301] - Công nghệ kỹ thuật điện, điện tử"},
    {"id": "7510302", "value": "[7510302] - Công nghệ kỹ thuật điện tử – viễn thông"},
    {"id": "7510303", "value": "[7510303] - Công nghệ kỹ thuật điều khiển và tự động hoá"},
    {"id": "7510304", "value": "[7510304] - IOT và Trí tuệ nhân tạo ứng dụng"},
    {"id": "7510306", "value": "[7510306] - Tự động hóa và tin học"},
    {"id": "7510401", "value": "[7510401] - Công nghệ kỹ thuật hóa học"},
    {"id": "7510402", "value": "[7510402] - Công nghệ vật liệu"},
    {"id": "7510403", "value": "[7510403] - Công nghệ kỹ thuật năng lượng"},
    {"id": "7510404", "value": "[7510404] - Kỹ thuật hoá phân tích"},
    {"id": "7510406", "value": "[7510406] - Công nghệ kỹ thuật môi trường"},
    {"id": "7510407", "value": "[7510407] - Công nghệ kỹ thuật hạt nhân"},
    {"id": "7510410", "value": "[7510410] - Công nghệ quan trắc và giám sát tài nguyên môi trường"},
    {"id": "7510601", "value": "[7510601] - Quản lý công nghiệp"},
    {"id": "7510602", "value": "[7510602] - Quản lý năng lượng"},
    {"id": "7510604", "value": "[7510604] - Kinh tế công nghiệp"},
    {"id": "7510605", "value": "[7510605] - Logistics và quản lý chuỗi cung ứng"},
    {"id": "7510606", "value": "[7510606] - Quản trị môi trường Doanh nghiệp"},
    {"id": "7510701", "value": "[7510701] - Công nghệ dầu khí và khai thác dầu"},
    {"id": "7510801", "value": "[7510801] - Công nghệ Kỹ thuật In"},
    {"id": "7519001", "value": "[7519001] - Công nghệ hàng không vũ trụ"},
    {"id": "7519002", "value": "[7519002] - Công nghệ nông nghiệp"},
    {"id": "7519003", "value": "[7519003] - Công nghệ kỹ thuật khuôn mẫu"},
    {"id": "7519007", "value": "[7519007] - Công nghệ Kỹ thuật năng lượng tái tạo"},
    {"id": "7520101", "value": "[7520101] - Cơ kỹ thuật"},
    {"id": "7520103", "value": "[7520103] - Kỹ thuật cơ khí"},
    {"id": "7520114", "value": "[7520114] - Kỹ thuật cơ điện tử"},
    {"id": "7520115", "value": "[7520115] - Kỹ thuật nhiệt"},
    {"id": "7520116", "value": "[7520116] - Kỹ thuật cơ khí động lực"},
    {"id": "7520117", "value": "[7520117] - Kỹ thuật công nghiệp"},
    {"id": "7520118", "value": "[7520118] - Kỹ thuật hệ thống công nghiệp"},
    {"id": "7520119", "value": "[7520119] - Kỹ thuật cơ điện tử thông minh và robot"},
    {"id": "7520120", "value": "[7520120] - Kỹ thuật hàng không"},
    {"id": "7520121", "value": "[7520121] - Kỹ thuật không gian"},
    {"id": "7520122", "value": "[7520122] - Kỹ thuật tàu thuỷ"},
    {"id": "7520130", "value": "[7520130] - Kỹ thuật ô tô"},
    {"id": "7520137", "value": "[7520137] - Kỹ thuật In"},
    {"id": "7520138", "value": "[7520138] - Kỹ thuật hàng hải"},
    {"id": "7520139", "value": "[7520139] - Kĩ thuật hệ thống công nghiệp và logistics"},
    {"id": "7520141", "value": "[7520141] - Công nghệ ô tô điện"},
    {"id": "7520201", "value": "[7520201] - Kỹ thuật điện"},
    {"id": "7520204", "value": "[7520204] - Kỹ thuật ra đa - dẫn đường"},
    {"id": "7520205", "value": "[7520205] - Kỹ thuật thuỷ âm"},
    {"id": "7520206", "value": "[7520206] - Kỹ thuật biển"},
    {"id": "7520207", "value": "[7520207] - Kỹ thuật điện tử - viễn thông"},
    {"id": "7520208", "value": "[7520208] -  Công nghệ internet vạn vật (IoT)"},
    {"id": "7520210", "value": "[7520210] - Kỹ thuật điện tử và tin học"},
    {"id": "7520212", "value": "[7520212] - Kỹ thuật y sinh"},
    {"id": "7520216", "value": "[7520216] - Kỹ thuật điều khiển và tự động hoá"},
    {"id": "7520217", "value": "[7520217] - Kỹ thuật Robot"},
    {"id": "7520218", "value": "[7520218] - Kỹ thuật Robot và Trí tuệ nhân tạo"},
    {"id": "7520219", "value": "[7520219] - Hệ thống giao thông thông minh"},
    {"id": "7520301", "value": "[7520301] - Kỹ thuật hoá học"},
    {"id": "7520309", "value": "[7520309] - Kỹ thuật vật liệu"},
    {"id": "7520310", "value": "[7520310] - Kỹ thuật vật liệu kim loại"},
    {"id": "7520312", "value": "[7520312] - Kỹ thuật dệt"},
    {"id": "7520320", "value": "[7520320] - Kỹ thuật môi trường"},
    {"id": "7520401", "value": "[7520401] - Vật lý kỹ thuật"},
    {"id": "7520402", "value": "[7520402] - Kỹ thuật hạt nhân"},
    {"id": "7520403", "value": "[7520403] - Vật lý y khoa, khối ngành"},
    {"id": "7520406", "value": "[7520406] - Kỹ thuật năng lượng"},
    {"id": "7520501", "value": "[7520501] - Kỹ thuật địa chất"},
    {"id": "7520502", "value": "[7520502] - Kỹ thuật địa vật lý"},
    {"id": "7520503", "value": "[7520503] - Kỹ thuật trắc địa - bản đồ"},
    {"id": "7520505", "value": "[7520505] - Đá quý Đá mỹ nghệ"},
    {"id": "7520601", "value": "[7520601] - Kỹ thuật mỏ"},
    {"id": "7520602", "value": "[7520602] - Kỹ thuật thăm dò và khảo sát"},
    {"id": "7520604", "value": "[7520604] - Kỹ thuật dầu khí"},
    {"id": "7520605", "value": "[7520605] - Kỹ thuật khí thiên nhiên"},
    {"id": "7520606", "value": "[7520606] - Công nghệ số trong thăm dò và khai thác tài nguyên thiên nhiên"},
    {"id": "7520607", "value": "[7520607] - Kỹ thuật tuyển khoáng"},
    {"id": "7540101", "value": "[7540101] - Công nghệ thực phẩm"},
    {"id": "7540102", "value": "[7540102] - Kỹ thuật thực phẩm"},
    {"id": "7540103", "value": "[7540103] - Công nghệ hóa thực phẩm"},
    {"id": "7540104", "value": "[7540104] - Công nghệ sau thu hoạch"},
    {"id": "7540105", "value": "[7540105] - Công nghệ chế biến thuỷ sản"},
    {"id": "7540106", "value": "[7540106] - Đảm bảo chất lượng và an toàn thực phẩm"},
    {"id": "7540108", "value": "[7540108] - Công nghệ và kinh doanh thực phẩm"},
    {"id": "7540110", "value": "[7540110] - Khoa học và công nghệ thực phẩm"},
    {"id": "7540202", "value": "[7540202] - Công nghệ sợi, dệt"},
    {"id": "7540203", "value": "[7540203] - Công nghệ vật liệu dệt, may"},
    {"id": "7540204", "value": "[7540204] - Công nghệ may"},
    {"id": "7540206", "value": "[7540206] - Công nghệ da giày"},
    {"id": "7540209", "value": "[7540209] - Công nghệ may"},
    {"id": "7549001", "value": "[7549001] - Công nghệ chế biến lâm sản"},
    {"id": "7549002", "value": "[7549002] - Kỹ nghệ gỗ và nội thất"},
    {"id": "7580101", "value": "[7580101] - Kiến trúc"},
    {"id": "7580102", "value": "[7580102] - Kiến trúc cảnh quan"},
    {"id": "7580103", "value": "[7580103] - Kiến trúc nội thất"},
    {"id": "7580104", "value": "[7580104] - Kiến trúc đô thị"},
    {"id": "7580105", "value": "[7580105] - Quy hoạch vùng và đô thị"},
    {"id": "7580106", "value": "[7580106] - Quản lý đô thị và công trình"},
    {"id": "7580107", "value": "[7580107] - Quản lý đô thị"},
    {"id": "7580108", "value": "[7580108] - Thiết kế nội thất"},
    {"id": "7580109", "value": "[7580109] - Quản lý phát triển đô thị và bất động sản"},
    {"id": "7580111", "value": "[7580111] - Bảo tồn di sản kiến trúc - đô thị"},
    {"id": "7580112", "value": "[7580112] - Đô thị học"},
    {"id": "7580199", "value": "[7580199] - Thiết kế đô thị"},
    {"id": "7580201", "value": "[7580201] - Kỹ thuật xây dựng"},
    {"id": "7580202", "value": "[7580202] - Kỹ thuật xây dựng công trình thủy"},
    {"id": "7580203", "value": "[7580203] - Kỹ thuật xây dựng công trình biển"},
    {"id": "7580204", "value": "[7580204] - Xây dựng công trình ngầm thành phố và Hệ thống tàu điện ngầm"},
    {"id": "7580205", "value": "[7580205] - Kỹ thuật xây dựng công trình giao thông"},
    {"id": "7580210", "value": "[7580210] - Kỹ thuật cơ sở hạ tầng"},
    {"id": "7580211", "value": "[7580211] - Địa kỹ thuật xây dựng"},
    {"id": "7580212", "value": "[7580212] - Kỹ thuật tài nguyên nước"},
    {"id": "7580213", "value": "[7580213] - Kỹ thuật cấp thoát nước"},
    {"id": "7580301", "value": "[7580301] - Kinh tế xây dựng"},
    {"id": "7580302", "value": "[7580302] - Quản lý xây dựng"},
    {"id": "7589001", "value": "[7589001] - Thiết kế xanh"},
    {"id": "7620101", "value": "[7620101] - Nông nghiệp"},
    {"id": "7620102", "value": "[7620102] - Khuyến nông"},
    {"id": "7620103", "value": "[7620103] - Khoa học đất"},
    {"id": "7620105", "value": "[7620105] - Chăn nuôi"},
    {"id": "7620106", "value": "[7620106] - Chăn nuôi thú y"},
    {"id": "7620108", "value": "[7620108] - Phân bón và dinh dưỡng cây trồng"},
    {"id": "7620109", "value": "[7620109] - Nông học"},
    {"id": "7620110", "value": "[7620110] - Khoa học cây trồng"},
    {"id": "7620112", "value": "[7620112] - Bảo vệ thực vật"},
    {"id": "7620113", "value": "[7620113] - Công nghệ rau hoa quả và cảnh quan"},
    {"id": "7620114", "value": "[7620114] - Kinh doanh nông nghiệp"},
    {"id": "7620115", "value": "[7620115] - Kinh tế nông nghiệp"},
    {"id": "7620116", "value": "[7620116] - Phát triển nông thôn"},
    {"id": "7620118", "value": "[7620118] - Nông nghiệp công nghệ cao"},
    {"id": "7620119", "value": "[7620119] - Chăn nuôi thú y"},
    {"id": "7620201", "value": "[7620201] - Lâm học"},
    {"id": "7620202", "value": "[7620202] - Lâm nghiệp đô thị"},
    {"id": "7620205", "value": "[7620205] - Lâm sinh"},
    {"id": "7620211", "value": "[7620211] - Quản lý tài nguyên rừng"},
    {"id": "7620301", "value": "[7620301] - Nuôi trồng thuỷ sản"},
    {"id": "7620302", "value": "[7620302] - Bệnh học thủy sản"},
    {"id": "7620303", "value": "[7620303] - Khoa học thủy sản"},
    {"id": "7620304", "value": "[7620304] - Khai thác thuỷ sản"},
    {"id": "7620305", "value": "[7620305] - Quản lý thủy sản"},
    {"id": "7640101", "value": "[7640101] - Thú y"},
    {"id": "7720101", "value": "[7720101] - Y khoa"},
    {"id": "7720110", "value": "[7720110] - Y học dự phòng"},
    {"id": "7720115", "value": "[7720115] - Y học cổ truyền"},
    {"id": "7720201", "value": "[7720201] - Dược học"},
    {"id": "7720203", "value": "[7720203] - Hoá dược"},
    {"id": "7720301", "value": "[7720301] - Điều dưỡng"},
    {"id": "7720302", "value": "[7720302] - Hộ sinh"},
    {"id": "7720401", "value": "[7720401] - Dinh dưỡng"},
    {"id": "7720497", "value": "[7720497] - Dinh dưỡng và khoa học thực phẩm"},
    {"id": "7720501", "value": "[7720501] - Răng - Hàm - Mặt"},
    {"id": "7720502", "value": "[7720502] - Kỹ thuật phục hình răng"},
    {"id": "7720601", "value": "[7720601] - Kỹ thuật xét nghiệm y học"},
    {"id": "7720602", "value": "[7720602] - Kỹ thuật hình ảnh y học"},
    {"id": "7720603", "value": "[7720603] - Kỹ thuật phục hồi chức năng"},
    {"id": "7720699", "value": "[7720699] - Khúc xạ nhãn khoa"},
    {"id": "7720701", "value": "[7720701] - Y tế công cộng"},
    {"id": "7720801", "value": "[7720801] - Tổ chức và quản lý y tế"},
    {"id": "7720802", "value": "[7720802] - Quản lý bệnh viện"},
    {"id": "7729001", "value": "[7729001] - Y sinh học thể dục thể thao"},
    {"id": "7760101", "value": "[7760101] - Công tác xã hội"},
    {"id": "7760102", "value": "[7760102] - Công tác thanh thiếu niên"},
    {"id": "7760103", "value": "[7760103] - Hỗ trợ giáo dục người khuyết tật"},
    {"id": "7760104", "value": "[7760104] - Dân số và phát triển"},
    {"id": "7810101", "value": "[7810101] - Du lịch"},
    {"id": "7810102", "value": "[7810102] - Du lịch điện tử"},
    {"id": "7810103", "value": "[7810103] - Quản trị dịch vụ du lịch và lữ hành"},
    {"id": "7810104", "value": "[7810104] - Quản trị du lịch khách sạn"},
    {"id": "7810105", "value": "[7810105] - Du lịch địa chất"},
    {"id": "7810106", "value": "[7810106] - Văn hóa Du lịch"},
    {"id": "7810201", "value": "[7810201] - Quản trị khách sạn"},
    {"id": "7810202", "value": "[7810202] - Quản trị nhà hàng và Dịch vụ ăn uống"},
    {"id": "7810203", "value": "[7810203] - Quản trị Khách sạn - Nhà hàng"},
    {"id": "7810301", "value": "[7810301] - Quản lý thể dục thể thao"},
    {"id": "7810302", "value": "[7810302] - Huấn luyện thể thao"},
    {"id": "7810501", "value": "[7810501] - Kinh tế gia đình"},
    {"id": "7810502", "value": "[7810502] - Kỹ thuật nữ công"},
    {"id": "7819009", "value": "[7819009] - Khoa học dinh dưỡng và thực phẩm"},
    {"id": "7819010", "value": "[7819010] - Khoa học chế biến món ăn"},
    {"id": "7840101", "value": "[7840101] - Khai thác vận tải"},
    {"id": "7840102", "value": "[7840102] - Quản lý hoạt động bay"},
    {"id": "7840104", "value": "[7840104] - Kinh tế vận tải"},
    {"id": "7840106", "value": "[7840106] - Khoa học hàng hải"},
    {"id": "7840110", "value": "[7840110] - Quản lý và vận hành hạ tầng"},
    {"id": "7850101", "value": "[7850101] - Quản lý tài nguyên và môi trường"},
    {"id": "7850102", "value": "[7850102] - Kinh tế tài nguyên thiên nhiên"},
    {"id": "7850103", "value": "[7850103] - Quản lý đất đai"},
    {"id": "7850104", "value": "[7850104] - Du lịch sinh thái"},
    {"id": "7850105", "value": "[7850105] - Quản lý an toàn, sức khỏe và môi trường"},
    {"id": "7850106", "value": "[7850106] - Quản lý tài nguyên thiên nhiên"},
    {"id": "7850110", "value": "[7850110] - Quản lý phát triển đô thị và bất động sản"},
    {"id": "7850118", "value": "[7850118] - Quản lý bất động sản"},
    {"id": "7850195", "value": "[7850195] - Quản lý tổng hợp tài nguyên nước"},
    {"id": "7850197", "value": "[7850197] - Quản lý tài nguyên và môi trường biển đảo"},
    {"id": "7850198", "value": "[7850198] - Quản lý tài nguyên nước"},
    {"id": "7850199", "value": "[7850199] - Quản lý biển"},
    {"id": "7850201", "value": "[7850201] - Bảo hộ lao động"},
    {"id": "7850202", "value": "[7850202] - An toàn, Vệ sinh lao động"},
    {"id": "7859002", "value": "[7859002] - Tài nguyên và du lịch sinh thái"},
    {"id": "7859007", "value": "[7859007] - Cảnh quan và kỹ thuật hoa viên"},
    {"id": "7860101", "value": "[7860101] - Trinh sát an ninh"},
    {"id": "7860102", "value": "[7860102] - Trinh sát cảnh sát"},
    {"id": "7860103", "value": "[7860103] - Trinh sát kỹ thuật"},
    {"id": "7860104", "value": "[7860104] - Điều tra hình sự"},
    {"id": "7860107", "value": "[7860107] - Kỹ thuật Công an nhân dân"},
    {"id": "7860108", "value": "[7860108] - Kỹ thuật hình sự"},
    {"id": "7860109", "value": "[7860109] - Quản lý nhà nước về an ninh trật tự"},
    {"id": "7860110", "value": "[7860110] - Quản lý trật tự an toàn giao thông"},
    {"id": "7860111", "value": "[7860111] - Thi hành án hình sự và hỗ trợ tư pháp"},
    {"id": "7860112", "value": "[7860112] - Tham mưu, chỉ huy công an nhân dân"},
    {"id": "7860113", "value": "[7860113] - Phòng cháy chữa cháy và cứu nạn cứu hộ"},
    {"id": "7860116", "value": "[7860116] - Hậu cần công an nhân dân"},
    {"id": "7860117", "value": "[7860117] - Tình báo an ninh"},
    {"id": "7860201", "value": "[7860201] - Chỉ huy tham mưu Lục quân"},
    {"id": "7860202", "value": "[7860202] - Chỉ huy tham mưu Hải quân"},
    {"id": "7860203", "value": "[7860203] - Chỉ huy tham mưu Không quân"},
    {"id": "7860204", "value": "[7860204] - Chỉ huy tham mưu Phòng không"},
    {"id": "7860205", "value": "[7860205] - Chỉ huy tham mưu Pháo binh"},
    {"id": "7860206", "value": "[7860206] - Chỉ huy tham mưu Tăng - thiết giáp"},
    {"id": "7860207", "value": "[7860207] - Chỉ huy tham mưu Đặc công"},
    {"id": "7860214", "value": "[7860214] - Biên phòng"},
    {"id": "7860217", "value": "[7860217] - Tình báo quân sự"},
    {"id": "7860218", "value": "[7860218] - Hậu cần quân sự"},
    {"id": "7860219", "value": "[7860219] - Chỉ huy, tham mưu thông tin"},
    {"id": "7860220", "value": "[7860220] - Chỉ huy, quản lý kỹ thuật"},
    {"id": "7860221", "value": "[7860221] - Chỉ huy, quản lý kỹ thuật"},
    {"id": "7860222", "value": "[7860222] - Quân sự cơ sở"},
    {"id": "7860226", "value": "[7860226] - Chỉ huy kỹ thuật Phòng không"},
    {"id": "7860227", "value": "[7860227] - Chỉ huy kỹ thuật Tăng - thiết giáp"},
    {"id": "7860228", "value": "[7860228] - Chỉ huy kỹ thuật Công binh"},
    {"id": "7860229", "value": "[7860229] - Chỉ huy kỹ thuật Hoá học"},
    {"id": "7860231", "value": "[7860231] - Trinh sát kỹ thuật"},
    {"id": "7860232", "value": "[7860232] - Chỉ huy kỹ thuật Hải quân"},
    {"id": "7860233", "value": "[7860233] - Chỉ huy kỹ thuật tác chiến điện tử"},
    {"id": "7900101", "value": "[7900101] - Quản trị doanh nghiệp và công nghệ"},
    {"id": "7900102", "value": "[7900102] - Marketing và truyền thông"},
    {"id": "7900103", "value": "[7900103] - Quản trị nhân lực và nhân tài"},
    {"id": "7900104", "value": "[7900104] - Kinh tế tài chính"},
    {"id": "7900189", "value": "[7900189] - Quản trị và An ninh"},
    {"id": "7900204", "value": "[7900204] - Quản trị đô thị thông minh và bền vững"},
    {"id": "7900205", "value": "[7900205] - Quản trị tài nguyên di sản"},
    {"id": "khac", "value": "Khác"}
]